Workbook

Sheet Summary
A1: PT AUDIT MODELS — FULL COVERAGE (EPS × Multiple)
A2: Built 2026-07-07 (evening) — extends PT_Models_Top10.xlsx to all 56 rated names (28 Buy / 28 Hold). Green = pulls from name tabs. Excluded: OKLO (no PT by design), ENTG (PT under review), ACM/CORZ/WOLF (not rated). Refresh each tab at its print.
A4: Ticker | B4: Rating | C4: Price 7/7 | D4: PT | E4: Bear | F4: NTM EPS (cons) | G4: P/E @ price | H4: P/E @ PT | I4: Asymmetry | J4: Next print | K4: Audit flag
A5: BUY-RATED (28)
A6: GEV | B6: Buy | C6: =GEV!B4 | D6: =GEV!B5 | E6: =GEV!B6 | F6: =GEV!B9 | G6: =GEV!B10 | H6: =GEV!B11 | I6: =GEV!B16 | J6: Jul 22 | K6: ⚠️ 35x anchor ≠ PT (79x NTM) — re-anchor Jul 22
A7: CEG | B7: Buy | C7: =CEG!B4 | D7: =CEG!B5 | E7: =CEG!B6 | F7: =CEG!B9 | G7: =CEG!B10 | H7: =CEG!B11 | I7: =CEG!B16 | J7: Aug 6~ | K7: EBITDA primary; P/E view distorted. PJM Jul 14; 9% above bear
A8: NRG | B8: Buy | C8: =NRG!B4 | D8: =NRG!B5 | E8: =NRG!B6 | F8: =NRG!B9 | G8: =NRG!B10 | H8: =NRG!B11 | I8: =NRG!B16 | J8: Aug 4 | K8: Clean. PJM Jul 14 leg
A9: VST | B9: Buy | C9: =VST!B4 | D9: =VST!B5 | E9: =VST!B6 | F9: =VST!B9 | G9: =VST!B10 | H9: =VST!B11 | I9: =VST!B16 | J9: Aug 7 | K9: Reconcile dual bear ($145 MP vs $105 re-uw) at Aug 7 print
A10: MU | B10: Buy | C10: =MU!B4 | D10: =MU!B5 | E10: =MU!B6 | F10: =MU!B9 | G10: =MU!B10 | H10: =MU!B11 | I10: =MU!B16 | J10: Sep 25 | K10: Conservative vs cons ($120 < cons NTM $131.8). Close<$900 protocol armed
A11: AVGO | B11: Buy | C11: =AVGO!B4 | D11: =AVGO!B5 | E11: =AVGO!B6 | F11: =AVGO!B9 | G11: =AVGO!B10 | H11: =AVGO!B11 | I11: =AVGO!B16 | J11: Sep 3 | K11: EV/Rev anchor; anchor-migration question (Sep 3)
A12: LRCX | B12: Buy | C12: =LRCX!B4 | D12: =LRCX!B5 | E12: =LRCX!B6 | F12: =LRCX!B9 | G12: =LRCX!B10 | H12: =LRCX!B11 | I12: =LRCX!B16 | J12: Jul 29 | K12: Reconciles ~60–64x; Jul 29 adjudicates
A13: VRT | B13: Buy | C13: =VRT!B4 | D13: =VRT!B5 | E13: =VRT!B6 | F13: =VRT!B9 | G13: =VRT!B10 | H13: =VRT!B11 | I13: =VRT!B16 | J13: Jul 29 | K13: ⚠️ No logged multiple anchor — set at Jul 29 print
A14: ANET | B14: Buy | C14: =ANET!B4 | D14: =ANET!B5 | E14: =ANET!B6 | F14: =ANET!B9 | G14: =ANET!B10 | H14: =ANET!B11 | I14: =ANET!B16 | J14: Aug 4~ | K14: Asym 0.29x — weakest top-10 R/R; review Aug 4
A15: BE | B15: Buy | C15: =BE!B4 | D15: =BE!B5 | E15: =BE!B6 | F15: =BE!B9 | G15: =BE!B10 | H15: =BE!B11 | I15: =BE!B16 | J15: Jul 28 | K15: EV/Rev anchor; P/E n/a
A16: AMAT | B16: Buy | C16: =AMAT!B4 | D16: =AMAT!B5 | E16: =AMAT!B6 | F16: =AMAT!B9 | G16: =AMAT!B10 | H16: =AMAT!B11 | I16: =AMAT!B16 | J16: Aug 13 | K16: Bear = $350–400 range midpoint. PT hit 6/30 — forward PT question open
A17: APLD | B17: Buy | C17: =APLD!B4 | D17: =APLD!B5 | E17: =APLD!B6 | F17: =APLD!B9 | G17: =APLD!B10 | H17: =APLD!B11 | I17: =APLD!B16 | J17: Aug 20 | K17: EPS-negative — P/E n/a; EV/capacity framework (see note)
A18: CAT | B18: Buy | C18: =CAT!B4 | D18: =CAT!B5 | E18: =CAT!B6 | F18: =CAT!B9 | G18: =CAT!B10 | H18: =CAT!B11 | I18: =CAT!B16 | J18: Aug 4 | K18: Re-underwrite due Jul 29 print — NTM cons unverified at 7/2 entry
A19: CCJ | B19: Buy | C19: =CCJ!B4 | D19: =CCJ!B5 | E19: =CCJ!B6 | F19: =CCJ!B9 | G19: =CCJ!B10 | H19: =CCJ!B11 | I19: =CCJ!B16 | J19: Jul 31 | K19: ⚠️ Bear $107 ABOVE price — bear stale after −13% drawdown; refresh at Jul 31
A20: CLS | B20: Buy | C20: =CLS!B4 | D20: =CLS!B5 | E20: =CLS!B6 | F20: =CLS!B9 | G20: =CLS!B10 | H20: =CLS!B11 | I20: =CLS!B16 | J20: Jul 27 | K20: June-3 batch PT — anchor undocumented
A21: DLR | B21: Buy | C21: =DLR!B4 | D21: =DLR!B5 | E21: =DLR!B6 | F21: =DLR!B9 | G21: =DLR!B10 | H21: =DLR!B11 | I21: =DLR!B16 | J21: Jul 23 | K21: REIT — estimates are core-FFO-adjacent; P/E view approximate
A22: FN | B22: Buy | C22: =FN!B4 | D22: =FN!B5 | E22: =FN!B6 | F22: =FN!B9 | G22: =FN!B10 | H22: =FN!B11 | I22: =FN!B16 | J22: Aug 18 | K22: June-3 batch PT — anchor undocumented
A23: GNRC | B23: Buy | C23: =GNRC!B4 | D23: =GNRC!B5 | E23: =GNRC!B6 | F23: =GNRC!B9 | G23: =GNRC!B10 | H23: =GNRC!B11 | I23: =GNRC!B16 | J23: Jul 29 | K23: June-3 batch PT — anchor undocumented
A24: HUBB | B24: Buy | C24: =HUBB!B4 | D24: =HUBB!B5 | E24: =HUBB!B6 | F24: =HUBB!B9 | G24: =HUBB!B10 | H24: =HUBB!B11 | I24: =HUBB!B16 | J24: Jul 28~ | K24: June-3 batch PT — anchor undocumented
A25: IRM | B25: Buy | C25: =IRM!B4 | D25: =IRM!B5 | E25: =IRM!B6 | F25: =IRM!B9 | G25: =IRM!B10 | H25: =IRM!B11 | I25: =IRM!B16 | J25: Jul 30 | K25: REIT — estimates are AFFO-adjacent; P/E view approximate
A26: LITE | B26: Buy | C26: =LITE!B4 | D26: =LITE!B5 | E26: =LITE!B6 | F26: =LITE!B9 | G26: =LITE!B10 | H26: =LITE!B11 | I26: =LITE!B16 | J26: Aug 20 | K26: Revenue-multiple anchor; P/E secondary
A27: MOD | B27: Buy | C27: =MOD!B4 | D27: =MOD!B5 | E27: =MOD!B6 | F27: =MOD!B9 | G27: =MOD!B10 | H27: =MOD!B11 | I27: =MOD!B16 | J27: Jul 29 | K27: June-3 batch PT — anchor undocumented
A28: MP | B28: Buy | C28: =MP!B4 | D28: =MP!B5 | E28: =MP!B6 | F28: =MP!B9 | G28: =MP!B10 | H28: =MP!B11 | I28: =MP!B16 | J28: Aug 6 | K28: Near-zero EPS — P/E distorted; strategic-asset framework
A29: MRVL | B29: Buy | C29: =MRVL!B4 | D29: =MRVL!B5 | E29: =MRVL!B6 | F29: =MRVL!B9 | G29: =MRVL!B10 | H29: =MRVL!B11 | I29: =MRVL!B16 | J29: Aug 27 | K29: Queued from top-10 pass; anchor undocumented
A30: NBIS | B30: Buy | C30: =NBIS!B4 | D30: =NBIS!B5 | E30: =NBIS!B6 | F30: =NBIS!B9 | G30: =NBIS!B10 | H30: =NBIS!B11 | I30: =NBIS!B16 | J30: Aug 6~ | K30: EPS-negative — revenue-multiple name; P/E n/a
A31: SPXC | B31: Buy | C31: =SPXC!B4 | D31: =SPXC!B5 | E31: =SPXC!B6 | F31: =SPXC!B9 | G31: =SPXC!B10 | H31: =SPXC!B11 | I31: =SPXC!B16 | J31: Jul 30 | K31: June-3 batch PT — anchor undocumented
A32: UUUU | B32: Hold (Spec) | C32: =UUUU!B4 | D32: =UUUU!B5 | E32: =UUUU!B6 | F32: =UUUU!B9 | G32: =UUUU!B10 | H32: =UUUU!B11 | I32: =UUUU!B16 | J32: Aug 7 | K32: ⚠️ PT SUSPENDED 7/7 (was $25 — embedded 21x rev growth); downgraded Buy→Hold(Spec); position ratification owed
A33: XYL | B33: Buy | C33: =XYL!B4 | D33: =XYL!B5 | E33: =XYL!B6 | F33: =XYL!B9 | G33: =XYL!B10 | H33: =XYL!B11 | I33: =XYL!B16 | J33: Jul 28 | K33: Clean
A35: HOLD-RATED (28)
A36: ASML | B36: Hold | C36: =ASML!B4 | D36: =ASML!B5 | E36: =ASML!B6 | F36: =ASML!B9 | G36: =ASML!B10 | H36: =ASML!B11 | I36: =ASML!B16 | J36: Jul 15 | K36: ⚠️ PT stale + no bear — BOTH set at Jul 15 reset. Price back above stale PT
A37: BW | B37: Hold | C37: =BW!B4 | D37: =BW!B5 | E37: =BW!B6 | F37: =BW!B9 | G37: =BW!B10 | H37: =BW!B11 | I37: =BW!B16 | J37: Aug 10 | K37: EV/Rev name; P/E distorted. Upgrade ≤$9 (16% away) or refi/2nd hyperscaler
A38: COHR | B38: Hold | C38: =COHR!B4 | D38: =COHR!B5 | E38: =COHR!B6 | F38: =COHR!B9 | G38: =COHR!B10 | H38: =COHR!B11 | I38: =COHR!B16 | J38: Aug 12 | K38: ⚠️ No bear logged — asymmetry incomputable
A39: CRDO | B39: Hold | C39: =CRDO!B4 | D39: =CRDO!B5 | E39: =CRDO!B6 | F39: =CRDO!B9 | G39: =CRDO!B10 | H39: =CRDO!B11 | I39: =CRDO!B16 | J39: Sep 2 | K39: ⚠️ No bear logged. Was in Hold-PT-Watch band (−1.4%)
A40: EME | B40: Hold | C40: =EME!B4 | D40: =EME!B5 | E40: =EME!B6 | F40: =EME!B9 | G40: =EME!B10 | H40: =EME!B11 | I40: =EME!B16 | J40: Jul 30 | K40: Add zone ≤$660 (asym ≥1.9x); alert live. Q2 upgrade gate: RPO>$16.5B + EPS≥$7.50 + guide≥$31
A41: EQIX | B41: Hold | C41: =EQIX!B4 | D41: =EQIX!B5 | E41: =EQIX!B6 | F41: =EQIX!B9 | G41: =EQIX!B10 | H41: =EQIX!B11 | I41: =EQIX!B16 | J41: Jul 29 | K41: REIT (AFFO-adjacent) + ⚠️ no bear logged
A42: ETN | B42: Hold | C42: =ETN!B4 | D42: =ETN!B5 | E42: =ETN!B6 | F42: =ETN!B9 | G42: =ETN!B10 | H42: =ETN!B11 | I42: =ETN!B16 | J42: Aug 4 | K42: ⚠️ No bear logged — asymmetry incomputable
A43: FCEL | B43: Hold | C43: =FCEL!B4 | D43: =FCEL!B5 | E43: =FCEL!B6 | F43: =FCEL!B9 | G43: =FCEL!B10 | H43: =FCEL!B11 | I43: =FCEL!B16 | J43: Sep 1 (FQ) | K43: EPS-negative. $200M offering 7/7 AH (~10–11.5% dilution) — watch pricing
A44: FCX | B44: Hold | C44: =FCX!B4 | D44: =FCX!B5 | E44: =FCX!B6 | F44: =FCX!B9 | G44: =FCX!B10 | H44: =FCX!B11 | I44: =FCX!B16 | J44: Jul 23 | K44: ⚠️ No $-bear logged (commodity-deck bear) — asymmetry incomputable
A45: GLW | B45: Hold | C45: =GLW!B4 | D45: =GLW!B5 | E45: =GLW!B6 | F45: =GLW!B9 | G45: =GLW!B10 | H45: =GLW!B11 | I45: =GLW!B16 | J45: Jul 28 | K45: ⚠️ No bear logged. Retired from Hold-PT-Watch band 7/7 (−12%)
A46: HUT | B46: Hold | C46: =HUT!B4 | D46: =HUT!B5 | E46: =HUT!B6 | F46: =HUT!B9 | G46: =HUT!B10 | H46: =HUT!B11 | I46: =HUT!B16 | J46: Aug 6 | K46: EPS-negative + ⚠️ no bear logged
A47: INTC | B47: Hold | C47: =INTC!B4 | D47: =INTC!B5 | E47: =INTC!B6 | F47: =INTC!B9 | G47: =INTC!B10 | H47: =INTC!B11 | I47: =INTC!B16 | J47: Jul 23 | K47: Owed post-✗ PT reset — due at Jul 23 print (per Hold PT Watch)
A48: IREN | B48: Hold | C48: =IREN!B4 | D48: =IREN!B5 | E48: =IREN!B6 | F48: =IREN!B9 | G48: =IREN!B10 | H48: =IREN!B11 | I48: =IREN!B16 | J48: Aug 27 (FQ) | K48: EPS-negative + ⚠️ no bear logged. PT 81% above price — stale?
A49: KLAC | B49: Hold | C49: =KLAC!B4 | D49: =KLAC!B5 | E49: =KLAC!B6 | F49: =KLAC!B9 | G49: =KLAC!B10 | H49: =KLAC!B11 | I49: =KLAC!B16 | J49: Jul 28 | K49: Post-split estimates ($1.00/$1.13). Asym ~0.7x at close
A50: MKSI | B50: Hold | C50: =MKSI!B4 | D50: =MKSI!B5 | E50: =MKSI!B6 | F50: =MKSI!B9 | G50: =MKSI!B10 | H50: =MKSI!B11 | I50: =MKSI!B16 | J50: Aug 5 | K50: Upgrade gate: leverage <2.5x AND asym ≥1.5x (≤$318)
A51: MPWR | B51: Hold | C51: =MPWR!B4 | D51: =MPWR!B5 | E51: =MPWR!B6 | F51: =MPWR!B9 | G51: =MPWR!B10 | H51: =MPWR!B11 | I51: =MPWR!B16 | J51: Jul 30 | K51: ⚠️ No bear logged. PT 34% above price — stale?
A52: NVT | B52: Hold | C52: =NVT!B4 | D52: =NVT!B5 | E52: =NVT!B6 | F52: =NVT!B9 | G52: =NVT!B10 | H52: =NVT!B11 | I52: =NVT!B16 | J52: Jul 31 | K52: ⚠️ No bear logged — asymmetry incomputable
A53: ON | B53: Hold | C53: =ON!B4 | D53: =ON!B5 | E53: =ON!B6 | F53: =ON!B9 | G53: =ON!B10 | H53: =ON!B11 | I53: =ON!B16 | J53: Aug 3 | K53: Re-entry: synergy proof or $70–75 pullback
A54: PWR | B54: Hold | C54: =PWR!B4 | D54: =PWR!B5 | E54: =PWR!B6 | F54: =PWR!B9 | G54: =PWR!B10 | H54: =PWR!B11 | I54: =PWR!B16 | J54: Jul 30 | K54: ⚠️ No bear logged. Hold-PT-Watch band edge (−3.4%)
A55: SCCO | B55: Hold | C55: =SCCO!B4 | D55: =SCCO!B5 | E55: =SCCO!B6 | F55: =SCCO!B9 | G55: =SCCO!B10 | H55: =SCCO!B11 | I55: =SCCO!B16 | J55: Jul 28 | K55: ⚠️ ABOVE PT (+2.9%) + no bear — Rule-2 decision owed at Jul 28 print
A56: SNDK | B56: Hold | C56: =SNDK!B4 | D56: =SNDK!B5 | E56: =SNDK!B6 | F56: =SNDK!B9 | G56: =SNDK!B10 | H56: =SNDK!B11 | I56: =SNDK!B16 | J56: Aug 13 | K56: Now 19% BELOW stale PT — asymmetry flipped favorable into gate
A57: STX | B57: Hold | C57: =STX!B4 | D57: =STX!B5 | E57: =STX!B6 | F57: =STX!B9 | G57: =STX!B10 | H57: =STX!B11 | I57: =STX!B16 | J57: Jul 28 | K57: ⚠️ No bear logged. Deepen note before Jul 28 print
A58: TOELY | B58: Hold | C58: =TOELY!B4 | D58: =TOELY!B5 | E58: =TOELY!B6 | F58: =TOELY!B9 | G58: =TOELY!B10 | H58: =TOELY!B11 | I58: =TOELY!B16 | J58: Jul 31 (est) | K58: No US consensus — vault EPS input. Upgrade: FY27H1 ¥-EPS ≥¥1,900 or ≤$150
A59: TSEM | B59: Hold | C59: =TSEM!B4 | D59: =TSEM!B5 | E59: =TSEM!B6 | F59: =TSEM!B9 | G59: =TSEM!B10 | H59: =TSEM!B11 | I59: =TSEM!B16 | J59: Aug 6 | K59: ⚠️ No bear logged — asymmetry incomputable
A60: TT | B60: Hold | C60: =TT!B4 | D60: =TT!B5 | E60: =TT!B6 | F60: =TT!B9 | G60: =TT!B10 | H60: =TT!B11 | I60: =TT!B16 | J60: Jul 29 | K60: ⚠️ No bear logged — asymmetry incomputable
A61: WDC | B61: Hold | C61: =WDC!B4 | D61: =WDC!B5 | E61: =WDC!B6 | F61: =WDC!B9 | G61: =WDC!B10 | H61: =WDC!B11 | I61: =WDC!B16 | J61: Jul 29 | K61: ⚠️ No bear logged. Retired from watch band 7/7; deepen before Jul 29 print
A62: WMB | B62: Hold | C62: =WMB!B4 | D62: =WMB!B5 | E62: =WMB!B6 | F62: =WMB!B9 | G62: =WMB!B10 | H62: =WMB!B11 | I62: =WMB!B16 | J62: Aug 3 | K62: Upgrade ≤$65 or Transco acceleration Aug 3. Green through the unwind
A63: SMNEY | B63: Hold | C63: =SMNEY!B4 | D63: =SMNEY!B5 | E63: =SMNEY!B6 | F63: =SMNEY!B9 | G63: =SMNEY!B10 | H63: =SMNEY!B11 | I63: =SMNEY!B16 | J63: Aug 6 (est) | K63: Derived pricing only (never FMP/OTC feeds). ENR.DE €155.30 × 0.2 × 1.1416 ⇒ ~$35.46
A66: SYSTEMATIC FINDINGS (7/7 build):
A67: 1. RESOLVED 7/7 evening — screening bears set for all 16 (trough-mult × NTM, per-name basis on each tab, blue inputs); ASML bear still by-design at Jul 15 reset. REFINE EACH AT ITS PRINT. All 16 asym <1.5x — Hold ratings validated; IREN 1.47x closest to Buy bar; SCCO negative (above PT).
A68: 2. RESOLVED 7/7 evening — implied anchors retro-documented (P/E@PT baseline, blue inputs on tabs; gap reads 0% by construction — meaningful only as drift baseline from here).
A69: 3. CCJ bear $107 is ABOVE the $94.67 price after the unwind — bear stale; refresh at Jul 31 print.
A70: 4. RESOLVED 7/7 evening — revenue-framework blocks added to the 8 EPS-negative/near-zero tabs (rows 31–44). KEY FINDINGS: UUUU PT $25 implies ~$1.25B NTM revenue vs $66M FY2025 actual (~19x embedded growth) — PT re-underwrite recommended; MP implies ~$2.0B vs $224M run-rate (~9x); APLD implies ~$4.3B (run-rate input to fill at Jul 29 print); NBIS implies ~$7.4B vs $1.6B annualized (~4.6x — aggressive but consistent with +684% YoY); BW reconciles cleanly ($857M implied ≈ $950M FY26E logged ✓). HUT/IREN have no revenue anchor — asset-based bear work owed at their prints.
A71: 5. Stale PTs gated to prints: ASML (Jul 15), SNDK (Aug 13), INTC reset owed (Jul 23). SCCO above PT with no bear — Rule-2 decision owed Jul 28.
A72: 6. REIT-adjacent estimates (DLR, EQIX, IRM) are FFO-like — P/E columns approximate.

Sheet GEV
A1: GEV — PT Audit Model (EPS × multiple) — Buy
A2: Built 2026-07-07 (evening). Consensus: Robinhood quarterly estimates 7/7 (next two quarters; NTM = 2 × sum — approximation, refine as quarters print). Prices: FMP official closes 7/7. Blue = input, Black = formula.
A4: Current price ($) | B4: 1077.08
A5: Our PT ($) | B5: 1200
A6: Bear ($) | B6: 600
A7: Cons EPS — Q+1e | B7: 3.22
A8: Cons EPS — Q+2e | B8: 4.33
A9: NTM EPS (approx = 2×(B7+B8)) | B9: =2*(B7+B8)
A10: P/E at current price | B10: =IF($B$9<=0,"n/m",B4/$B$9)
A11: P/E implied at PT | B11: =IF($B$9<=0,"n/m",B5/$B$9)
A12: P/E implied at bear | B12: =IF($B$9<=0,"n/m",B6/$B$9)
A13: Stated multiple anchor | B13: 35
A14: Required NTM EPS for PT at stated mult | B14: =IF(ISNUMBER(B13),B5/B13,"—")
A15: Consensus NTM vs required (gap) | B15: =IF(AND(ISNUMBER(B14),ISNUMBER(B9),B9>0),B9/B14-1,"—")
A16: Asymmetry (PT−P)/(P−bear) | B16: =(B5-B4)/(B4-B6)
A18: Methodology (as logged in Decisions Log / note):
A19: Thesis-driven — logged as 'NTM P/E 35x' (6/3)
A21: Implied price grid — NTM EPS (rows) × multiple (cols). All formulas.
A22: EPS \ Mult | B22: =IF(ISNUMBER(B12),ROUND(B12,1),ROUND(B10*0.7,1)) | C22: =ROUND(B10,1) | D22: =ROUND(B11,1)
A23: =ROUND($B$9*0.85,2) | B23: =$A23*B$22 | C23: =$A23*C$22 | D23: =$A23*D$22
A24: =ROUND($B$9*1,2) | B24: =$A24*B$22 | C24: =$A24*C$22 | D24: =$A24*D$22
A25: =ROUND($B$9*1.15,2) | B25: =$A25*B$22 | C25: =$A25*C$22 | D25: =$A25*D$22
A27: Audit note:
A28: ⚠️ 35x anchor ≠ PT (79x NTM) — re-anchor Jul 22

Sheet CEG
A1: CEG — PT Audit Model (EPS × multiple) — Buy
A2: Built 2026-07-07 (evening). Consensus: Robinhood quarterly estimates 7/7 (next two quarters; NTM = 2 × sum — approximation, refine as quarters print). Prices: FMP official closes 7/7. Blue = input, Black = formula.
A4: Current price ($) | B4: 239.71
A5: Our PT ($) | B5: 385
A6: Bear ($) | B6: 220
A7: Cons EPS — Q+1e | B7: 2.37
A8: Cons EPS — Q+2e | B8: 3.84
A9: NTM EPS (approx = 2×(B7+B8)) | B9: =2*(B7+B8)
A10: P/E at current price | B10: =IF($B$9<=0,"n/m",B4/$B$9)
A11: P/E implied at PT | B11: =IF($B$9<=0,"n/m",B5/$B$9)
A12: P/E implied at bear | B12: =IF($B$9<=0,"n/m",B6/$B$9)
A13: Stated multiple anchor | B13: —
A14: Required NTM EPS for PT at stated mult | B14: —
A15: Consensus NTM vs required (gap) | B15: —
A16: Asymmetry (PT−P)/(P−bear) | B16: =(B5-B4)/(B4-B6)
A18: Methodology (as logged in Decisions Log / note):
A19: DCF + variant perception (EV/EBITDA; 14x exit in DCF)
A21: Implied price grid — NTM EPS (rows) × multiple (cols). All formulas.
A22: EPS \ Mult | B22: =IF(ISNUMBER(B12),ROUND(B12,1),ROUND(B10*0.7,1)) | C22: =ROUND(B10,1) | D22: =ROUND(B11,1)
A23: =ROUND($B$9*0.85,2) | B23: =$A23*B$22 | C23: =$A23*C$22 | D23: =$A23*D$22
A24: =ROUND($B$9*1,2) | B24: =$A24*B$22 | C24: =$A24*C$22 | D24: =$A24*D$22
A25: =ROUND($B$9*1.15,2) | B25: =$A25*B$22 | C25: =$A25*C$22 | D25: =$A25*D$22
A27: Audit note:
A28: EBITDA primary; P/E view distorted. PJM Jul 14; 9% above bear

Sheet NRG
A1: NRG — PT Audit Model (EPS × multiple) — Buy
A2: Built 2026-07-07 (evening). Consensus: Robinhood quarterly estimates 7/7 (next two quarters; NTM = 2 × sum — approximation, refine as quarters print). Prices: FMP official closes 7/7. Blue = input, Black = formula.
A4: Current price ($) | B4: 138.01
A5: Our PT ($) | B5: 185
A6: Bear ($) | B6: 110
A7: Cons EPS — Q+1e | B7: 1.75
A8: Cons EPS — Q+2e | B8: 3.24
A9: NTM EPS (approx = 2×(B7+B8)) | B9: =2*(B7+B8)
A10: P/E at current price | B10: =IF($B$9<=0,"n/m",B4/$B$9)
A11: P/E implied at PT | B11: =IF($B$9<=0,"n/m",B5/$B$9)
A12: P/E implied at bear | B12: =IF($B$9<=0,"n/m",B6/$B$9)
A13: Stated multiple anchor | B13: —
A14: Required NTM EPS for PT at stated mult | B14: —
A15: Consensus NTM vs required (gap) | B15: —
A16: Asymmetry (PT−P)/(P−bear) | B16: =(B5-B4)/(B4-B6)
A18: Methodology (as logged in Decisions Log / note):
A19: Variant perception (6/3)
A21: Implied price grid — NTM EPS (rows) × multiple (cols). All formulas.
A22: EPS \ Mult | B22: =IF(ISNUMBER(B12),ROUND(B12,1),ROUND(B10*0.7,1)) | C22: =ROUND(B10,1) | D22: =ROUND(B11,1)
A23: =ROUND($B$9*0.85,2) | B23: =$A23*B$22 | C23: =$A23*C$22 | D23: =$A23*D$22
A24: =ROUND($B$9*1,2) | B24: =$A24*B$22 | C24: =$A24*C$22 | D24: =$A24*D$22
A25: =ROUND($B$9*1.15,2) | B25: =$A25*B$22 | C25: =$A25*C$22 | D25: =$A25*D$22
A27: Audit note:
A28: Clean. PJM Jul 14 leg

Sheet VST
A1: VST — PT Audit Model (EPS × multiple) — Buy
A2: Built 2026-07-07 (evening). Consensus: Robinhood quarterly estimates 7/7 (next two quarters; NTM = 2 × sum — approximation, refine as quarters print). Prices: FMP official closes 7/7. Blue = input, Black = formula.
A4: Current price ($) | B4: 155.73
A5: Our PT ($) | B5: 230
A6: Bear ($) | B6: 145
A7: Cons EPS — Q+1e | B7: 2.21
A8: Cons EPS — Q+2e | B8: 2.37
A9: NTM EPS (approx = 2×(B7+B8)) | B9: =2*(B7+B8)
A10: P/E at current price | B10: =IF($B$9<=0,"n/m",B4/$B$9)
A11: P/E implied at PT | B11: =IF($B$9<=0,"n/m",B5/$B$9)
A12: P/E implied at bear | B12: =IF($B$9<=0,"n/m",B6/$B$9)
A13: Stated multiple anchor | B13: —
A14: Required NTM EPS for PT at stated mult | B14: —
A15: Consensus NTM vs required (gap) | B15: —
A16: Asymmetry (PT−P)/(P−bear) | B16: =(B5-B4)/(B4-B6)
A18: Methodology (as logged in Decisions Log / note):
A19: Variant perception; bear re-underwritten 6/23 (9x $6.5B EBITDA ⇒ ~$105; MP bear $145)
A21: Implied price grid — NTM EPS (rows) × multiple (cols). All formulas.
A22: EPS \ Mult | B22: =IF(ISNUMBER(B12),ROUND(B12,1),ROUND(B10*0.7,1)) | C22: =ROUND(B10,1) | D22: =ROUND(B11,1)
A23: =ROUND($B$9*0.85,2) | B23: =$A23*B$22 | C23: =$A23*C$22 | D23: =$A23*D$22
A24: =ROUND($B$9*1,2) | B24: =$A24*B$22 | C24: =$A24*C$22 | D24: =$A24*D$22
A25: =ROUND($B$9*1.15,2) | B25: =$A25*B$22 | C25: =$A25*C$22 | D25: =$A25*D$22
A27: Audit note:
A28: Reconcile dual bear ($145 MP vs $105 re-uw) at Aug 7 print

Sheet MU
A1: MU — PT Audit Model (EPS × multiple) — Buy
A2: Built 2026-07-07 (evening). Consensus: Robinhood quarterly estimates 7/7 (next two quarters; NTM = 2 × sum — approximation, refine as quarters print). Prices: FMP official closes 7/7. Blue = input, Black = formula.
A4: Current price ($) | B4: 938.38
A5: Our PT ($) | B5: 1500
A6: Bear ($) | B6: 900
A7: Cons EPS — Q+1e | B7: 31.24
A8: Cons EPS — Q+2e | B8: 34.66
A9: NTM EPS (approx = 2×(B7+B8)) | B9: =2*(B7+B8)
A10: P/E at current price | B10: =IF($B$9<=0,"n/m",B4/$B$9)
A11: P/E implied at PT | B11: =IF($B$9<=0,"n/m",B5/$B$9)
A12: P/E implied at bear | B12: =IF($B$9<=0,"n/m",B6/$B$9)
A13: Stated multiple anchor | B13: 12.5
A14: Required NTM EPS for PT at stated mult | B14: =IF(ISNUMBER(B13),B5/B13,"—")
A15: Consensus NTM vs required (gap) | B15: =IF(AND(ISNUMBER(B14),ISNUMBER(B9),B9>0),B9/B14-1,"—")
A16: Asymmetry (PT−P)/(P−bear) | B16: =(B5-B4)/(B4-B6)
A18: Methodology (as logged in Decisions Log / note):
A19: Catalyst Playbook upgrade (6/25) — 12.5x NTM ~$120
A21: Implied price grid — NTM EPS (rows) × multiple (cols). All formulas.
A22: EPS \ Mult | B22: =IF(ISNUMBER(B12),ROUND(B12,1),ROUND(B10*0.7,1)) | C22: =ROUND(B10,1) | D22: =ROUND(B11,1)
A23: =ROUND($B$9*0.85,2) | B23: =$A23*B$22 | C23: =$A23*C$22 | D23: =$A23*D$22
A24: =ROUND($B$9*1,2) | B24: =$A24*B$22 | C24: =$A24*C$22 | D24: =$A24*D$22
A25: =ROUND($B$9*1.15,2) | B25: =$A25*B$22 | C25: =$A25*C$22 | D25: =$A25*D$22
A27: Audit note:
A28: Conservative vs cons ($120 < cons NTM $131.8). Close<$900 protocol armed

Sheet AVGO
A1: AVGO — PT Audit Model (EPS × multiple) — Buy
A2: Built 2026-07-07 (evening). Consensus: Robinhood quarterly estimates 7/7 (next two quarters; NTM = 2 × sum — approximation, refine as quarters print). Prices: FMP official closes 7/7. Blue = input, Black = formula.
A4: Current price ($) | B4: 370.78
A5: Our PT ($) | B5: 560
A6: Bear ($) | B6: 350
A7: Cons EPS — Q+1e | B7: 3.16
A8: Cons EPS — Q+2e | B8: 3.79
A9: NTM EPS (approx = 2×(B7+B8)) | B9: =2*(B7+B8)
A10: P/E at current price | B10: =IF($B$9<=0,"n/m",B4/$B$9)
A11: P/E implied at PT | B11: =IF($B$9<=0,"n/m",B5/$B$9)
A12: P/E implied at bear | B12: =IF($B$9<=0,"n/m",B6/$B$9)
A13: Stated multiple anchor | B13: —
A14: Required NTM EPS for PT at stated mult | B14: —
A15: Consensus NTM vs required (gap) | B15: —
A16: Asymmetry (PT−P)/(P−bear) | B16: =(B5-B4)/(B4-B6)
A18: Methodology (as logged in Decisions Log / note):
A19: EV/Revenue ~14x NTM (initiation); Buy reaffirmed 7/7
A21: Implied price grid — NTM EPS (rows) × multiple (cols). All formulas.
A22: EPS \ Mult | B22: =IF(ISNUMBER(B12),ROUND(B12,1),ROUND(B10*0.7,1)) | C22: =ROUND(B10,1) | D22: =ROUND(B11,1)
A23: =ROUND($B$9*0.85,2) | B23: =$A23*B$22 | C23: =$A23*C$22 | D23: =$A23*D$22
A24: =ROUND($B$9*1,2) | B24: =$A24*B$22 | C24: =$A24*C$22 | D24: =$A24*D$22
A25: =ROUND($B$9*1.15,2) | B25: =$A25*B$22 | C25: =$A25*C$22 | D25: =$A25*D$22
A27: Audit note:
A28: EV/Rev anchor; anchor-migration question (Sep 3)

Sheet LRCX
A1: LRCX — PT Audit Model (EPS × multiple) — Buy
A2: Built 2026-07-07 (evening). Consensus: Robinhood quarterly estimates 7/7 (next two quarters; NTM = 2 × sum — approximation, refine as quarters print). Prices: FMP official closes 7/7. Blue = input, Black = formula.
A4: Current price ($) | B4: 326.13
A5: Our PT ($) | B5: 450
A6: Bear ($) | B6: 200
A7: Cons EPS — Q+1e | B7: 1.68
A8: Cons EPS — Q+2e | B8: 1.81
A9: NTM EPS (approx = 2×(B7+B8)) | B9: =2*(B7+B8)
A10: P/E at current price | B10: =IF($B$9<=0,"n/m",B4/$B$9)
A11: P/E implied at PT | B11: =IF($B$9<=0,"n/m",B5/$B$9)
A12: P/E implied at bear | B12: =IF($B$9<=0,"n/m",B6/$B$9)
A13: Stated multiple anchor | B13: 60
A14: Required NTM EPS for PT at stated mult | B14: =IF(ISNUMBER(B13),B5/B13,"—")
A15: Consensus NTM vs required (gap) | B15: =IF(AND(ISNUMBER(B14),ISNUMBER(B9),B9>0),B9/B14-1,"—")
A16: Asymmetry (PT−P)/(P−bear) | B16: =(B5-B4)/(B4-B6)
A18: Methodology (as logged in Decisions Log / note):
A19: Revised estimates (6/18) — ~60x FY27 EPS ~$7.25 ⇒ $435–472
A21: Implied price grid — NTM EPS (rows) × multiple (cols). All formulas.
A22: EPS \ Mult | B22: =IF(ISNUMBER(B12),ROUND(B12,1),ROUND(B10*0.7,1)) | C22: =ROUND(B10,1) | D22: =ROUND(B11,1)
A23: =ROUND($B$9*0.85,2) | B23: =$A23*B$22 | C23: =$A23*C$22 | D23: =$A23*D$22
A24: =ROUND($B$9*1,2) | B24: =$A24*B$22 | C24: =$A24*C$22 | D24: =$A24*D$22
A25: =ROUND($B$9*1.15,2) | B25: =$A25*B$22 | C25: =$A25*C$22 | D25: =$A25*D$22
A27: Audit note:
A28: Reconciles ~60–64x; Jul 29 adjudicates

Sheet VRT
A1: VRT — PT Audit Model (EPS × multiple) — Buy
A2: Built 2026-07-07 (evening). Consensus: Robinhood quarterly estimates 7/7 (next two quarters; NTM = 2 × sum — approximation, refine as quarters print). Prices: FMP official closes 7/7. Blue = input, Black = formula.
A4: Current price ($) | B4: 305.58
A5: Our PT ($) | B5: 370
A6: Bear ($) | B6: 220
A7: Cons EPS — Q+1e | B7: 1.43
A8: Cons EPS — Q+2e | B8: 1.79
A9: NTM EPS (approx = 2×(B7+B8)) | B9: =2*(B7+B8)
A10: P/E at current price | B10: =IF($B$9<=0,"n/m",B4/$B$9)
A11: P/E implied at PT | B11: =IF($B$9<=0,"n/m",B5/$B$9)
A12: P/E implied at bear | B12: =IF($B$9<=0,"n/m",B6/$B$9)
A13: Stated multiple anchor | B13: —
A14: Required NTM EPS for PT at stated mult | B14: —
A15: Consensus NTM vs required (gap) | B15: —
A16: Asymmetry (PT−P)/(P−bear) | B16: =(B5-B4)/(B4-B6)
A18: Methodology (as logged in Decisions Log / note):
A19: Thesis-driven (AI cooling pure-play); no logged multiple anchor
A21: Implied price grid — NTM EPS (rows) × multiple (cols). All formulas.
A22: EPS \ Mult | B22: =IF(ISNUMBER(B12),ROUND(B12,1),ROUND(B10*0.7,1)) | C22: =ROUND(B10,1) | D22: =ROUND(B11,1)
A23: =ROUND($B$9*0.85,2) | B23: =$A23*B$22 | C23: =$A23*C$22 | D23: =$A23*D$22
A24: =ROUND($B$9*1,2) | B24: =$A24*B$22 | C24: =$A24*C$22 | D24: =$A24*D$22
A25: =ROUND($B$9*1.15,2) | B25: =$A25*B$22 | C25: =$A25*C$22 | D25: =$A25*D$22
A27: Audit note:
A28: ⚠️ No logged multiple anchor — set at Jul 29 print

Sheet ANET
A1: ANET — PT Audit Model (EPS × multiple) — Buy
A2: Built 2026-07-07 (evening). Consensus: Robinhood quarterly estimates 7/7 (next two quarters; NTM = 2 × sum — approximation, refine as quarters print). Prices: FMP official closes 7/7. Blue = input, Black = formula.
A4: Current price ($) | B4: 166.46
A5: Our PT ($) | B5: 185
A6: Bear ($) | B6: 90
A7: Cons EPS — Q+1e | B7: 0.86
A8: Cons EPS — Q+2e | B8: 0.89
A9: NTM EPS (approx = 2×(B7+B8)) | B9: =2*(B7+B8)
A10: P/E at current price | B10: =IF($B$9<=0,"n/m",B4/$B$9)
A11: P/E implied at PT | B11: =IF($B$9<=0,"n/m",B5/$B$9)
A12: P/E implied at bear | B12: =IF($B$9<=0,"n/m",B6/$B$9)
A13: Stated multiple anchor | B13: —
A14: Required NTM EPS for PT at stated mult | B14: —
A15: Consensus NTM vs required (gap) | B15: —
A16: Asymmetry (PT−P)/(P−bear) | B16: =(B5-B4)/(B4-B6)
A18: Methodology (as logged in Decisions Log / note):
A19: Thesis-driven (AI Ethernet)
A21: Implied price grid — NTM EPS (rows) × multiple (cols). All formulas.
A22: EPS \ Mult | B22: =IF(ISNUMBER(B12),ROUND(B12,1),ROUND(B10*0.7,1)) | C22: =ROUND(B10,1) | D22: =ROUND(B11,1)
A23: =ROUND($B$9*0.85,2) | B23: =$A23*B$22 | C23: =$A23*C$22 | D23: =$A23*D$22
A24: =ROUND($B$9*1,2) | B24: =$A24*B$22 | C24: =$A24*C$22 | D24: =$A24*D$22
A25: =ROUND($B$9*1.15,2) | B25: =$A25*B$22 | C25: =$A25*C$22 | D25: =$A25*D$22
A27: Audit note:
A28: Asym 0.29x — weakest top-10 R/R; review Aug 4

Sheet BE
A1: BE — PT Audit Model (EPS × multiple) — Buy
A2: Built 2026-07-07 (evening). Consensus: Robinhood quarterly estimates 7/7 (next two quarters; NTM = 2 × sum — approximation, refine as quarters print). Prices: FMP official closes 7/7. Blue = input, Black = formula.
A4: Current price ($) | B4: 269.57
A5: Our PT ($) | B5: 330
A6: Bear ($) | B6: 120
A7: Cons EPS — Q+1e | B7: 0.36
A8: Cons EPS — Q+2e | B8: 0.48
A9: NTM EPS (approx = 2×(B7+B8)) | B9: =2*(B7+B8)
A10: P/E at current price | B10: =IF($B$9<=0,"n/m",B4/$B$9)
A11: P/E implied at PT | B11: =IF($B$9<=0,"n/m",B5/$B$9)
A12: P/E implied at bear | B12: =IF($B$9<=0,"n/m",B6/$B$9)
A13: Stated multiple anchor | B13: —
A14: Required NTM EPS for PT at stated mult | B14: —
A15: Consensus NTM vs required (gap) | B15: —
A16: Asymmetry (PT−P)/(P−bear) | B16: =(B5-B4)/(B4-B6)
A18: Methodology (as logged in Decisions Log / note):
A19: EV/Revenue (per valuation snapshot)
A21: Implied price grid — NTM EPS (rows) × multiple (cols). All formulas.
A22: EPS \ Mult | B22: =IF(ISNUMBER(B12),ROUND(B12,1),ROUND(B10*0.7,1)) | C22: =ROUND(B10,1) | D22: =ROUND(B11,1)
A23: =ROUND($B$9*0.85,2) | B23: =$A23*B$22 | C23: =$A23*C$22 | D23: =$A23*D$22
A24: =ROUND($B$9*1,2) | B24: =$A24*B$22 | C24: =$A24*C$22 | D24: =$A24*D$22
A25: =ROUND($B$9*1.15,2) | B25: =$A25*B$22 | C25: =$A25*C$22 | D25: =$A25*D$22
A27: Audit note:
A28: EV/Rev anchor; P/E n/a

Sheet AMAT
A1: AMAT — PT Audit Model (EPS × multiple) — Buy
A2: Built 2026-07-07 (evening). Consensus: Robinhood quarterly estimates 7/7 (next two quarters; NTM = 2 × sum — approximation, refine as quarters print). Prices: FMP official closes 7/7. Blue = input, Black = formula.
A4: Current price ($) | B4: 554.5
A5: Our PT ($) | B5: 680
A6: Bear ($) | B6: 375
A7: Cons EPS — Q+1e | B7: 2.91
A8: Cons EPS — Q+2e | B8: 3.59
A9: NTM EPS (approx = 2×(B7+B8)) | B9: =2*(B7+B8)
A10: P/E at current price | B10: =IF($B$9<=0,"n/m",B4/$B$9)
A11: P/E implied at PT | B11: =IF($B$9<=0,"n/m",B5/$B$9)
A12: P/E implied at bear | B12: =IF($B$9<=0,"n/m",B6/$B$9)
A13: Stated multiple anchor | B13: —
A14: Required NTM EPS for PT at stated mult | B14: —
A15: Consensus NTM vs required (gap) | B15: —
A16: Asymmetry (PT−P)/(P−bear) | B16: =(B5-B4)/(B4-B6)
A18: Methodology (as logged in Decisions Log / note):
A19: Comps/NTM P/E — PT $520→$680 (6/19); closed ✓ 6/30 at $723
A21: Implied price grid — NTM EPS (rows) × multiple (cols). All formulas.
A22: EPS \ Mult | B22: =IF(ISNUMBER(B12),ROUND(B12,1),ROUND(B10*0.7,1)) | C22: =ROUND(B10,1) | D22: =ROUND(B11,1)
A23: =ROUND($B$9*0.85,2) | B23: =$A23*B$22 | C23: =$A23*C$22 | D23: =$A23*D$22
A24: =ROUND($B$9*1,2) | B24: =$A24*B$22 | C24: =$A24*C$22 | D24: =$A24*D$22
A25: =ROUND($B$9*1.15,2) | B25: =$A25*B$22 | C25: =$A25*C$22 | D25: =$A25*D$22
A27: Audit note:
A28: Bear = $350–400 range midpoint. PT hit 6/30 — forward PT question open

Sheet APLD
A1: APLD — PT Audit Model (EPS × multiple) — Buy
A2: Built 2026-07-07 (evening). Consensus: Robinhood quarterly estimates 7/7 (next two quarters; NTM = 2 × sum — approximation, refine as quarters print). Prices: FMP official closes 7/7. Blue = input, Black = formula.
A4: Current price ($) | B4: 30.71
A5: Our PT ($) | B5: 60
A6: Bear ($) | B6: 20
A7: Cons EPS — Q+1e | B7: -0.36
A8: Cons EPS — Q+2e | B8: -0.2
A9: NTM EPS (approx = 2×(B7+B8)) | B9: =2*(B7+B8)
A10: P/E at current price | B10: =IF($B$9<=0,"n/m",B4/$B$9)
A11: P/E implied at PT | B11: =IF($B$9<=0,"n/m",B5/$B$9)
A12: P/E implied at bear | B12: =IF($B$9<=0,"n/m",B6/$B$9)
A13: Stated multiple anchor | B13: —
A14: Required NTM EPS for PT at stated mult | B14: —
A15: Consensus NTM vs required (gap) | B15: —
A16: Asymmetry (PT−P)/(P−bear) | B16: =(B5-B4)/(B4-B6)
A18: Methodology (as logged in Decisions Log / note):
A19: Thesis-driven (DC capacity + CoreWeave leases)
A21: Grid omitted — EPS-negative / derived-price name; P/E framework not meaningful.
A27: Audit note:
A28: EPS-negative — P/E n/a; EV/capacity framework (see note)
A31: REVENUE FRAMEWORK (added 7/7 evening — EPS-negative/near-zero name)
A32: Vault anchors used (consensus revenue unavailable on current data plan); audit = growth embedded in the PT.
A33: Market cap 7/7 ($B) | B33: 8.776
A34: Net debt ($B) | B34: —
A35: Vault revenue anchor (EV/Rev x) | B35: 4
A36: Run-rate revenue ($B) | B36: [FILL] | C36: [FILL — pull latest quarterly run-rate; Q4 FY2026 prints Jul 29]
A37: Cap @ PT ($B) | B37: =B33*B5/B4
A38: EV @ PT ($B) | B38: =B37+IF(ISNUMBER(B34),B34,0)
A39: Implied NTM revenue the PT requires ($B) | B39: =IF(ISNUMBER(B35),B38/B35,"—")
A40: Growth embedded: implied rev ÷ run-rate | B40: =IF(AND(ISNUMBER(B39),ISNUMBER(B36)),B39/B36,"—")
A41: P/S at price (run-rate) | B41: =IF(ISNUMBER(B36),B33/B36,"—")
A43: Note:
A44: EV/Rev 4x anchor. Net debt [VERIFY — refi was the 6/3 risk].

Sheet CAT
A1: CAT — PT Audit Model (EPS × multiple) — Buy
A2: Built 2026-07-07 (evening). Consensus: Robinhood quarterly estimates 7/7 (next two quarters; NTM = 2 × sum — approximation, refine as quarters print). Prices: FMP official closes 7/7. Blue = input, Black = formula.
A4: Current price ($) | B4: 940.12
A5: Our PT ($) | B5: 1150
A6: Bear ($) | B6: 620
A7: Cons EPS — Q+1e | B7: 5.71
A8: Cons EPS — Q+2e | B8: 6.44
A9: NTM EPS (approx = 2×(B7+B8)) | B9: =2*(B7+B8)
A10: P/E at current price | B10: =IF($B$9<=0,"n/m",B4/$B$9)
A11: P/E implied at PT | B11: =IF($B$9<=0,"n/m",B5/$B$9)
A12: P/E implied at bear | B12: =IF($B$9<=0,"n/m",B6/$B$9)
A13: Stated multiple anchor | B13: 40
A14: Required NTM EPS for PT at stated mult | B14: =IF(ISNUMBER(B13),B5/B13,"—")
A15: Consensus NTM vs required (gap) | B15: =IF(AND(ISNUMBER(B14),ISNUMBER(B9),B9>0),B9/B14-1,"—")
A16: Asymmetry (PT−P)/(P−bear) | B16: =(B5-B4)/(B4-B6)
A18: Methodology (as logged in Decisions Log / note):
A19: Comps 40x NTM ~$28.75, consensus-anchored (7/2, Screening Mode)
A21: Implied price grid — NTM EPS (rows) × multiple (cols). All formulas.
A22: EPS \ Mult | B22: =IF(ISNUMBER(B12),ROUND(B12,1),ROUND(B10*0.7,1)) | C22: =ROUND(B10,1) | D22: =ROUND(B11,1)
A23: =ROUND($B$9*0.85,2) | B23: =$A23*B$22 | C23: =$A23*C$22 | D23: =$A23*D$22
A24: =ROUND($B$9*1,2) | B24: =$A24*B$22 | C24: =$A24*C$22 | D24: =$A24*D$22
A25: =ROUND($B$9*1.15,2) | B25: =$A25*B$22 | C25: =$A25*C$22 | D25: =$A25*D$22
A27: Audit note:
A28: Re-underwrite due Jul 29 print — NTM cons unverified at 7/2 entry

Sheet CCJ
A1: CCJ — PT Audit Model (EPS × multiple) — Buy
A2: Built 2026-07-07 (evening). Consensus: Robinhood quarterly estimates 7/7 (next two quarters; NTM = 2 × sum — approximation, refine as quarters print). Prices: FMP official closes 7/7. Blue = input, Black = formula.
A4: Current price ($) | B4: 94.67
A5: Our PT ($) | B5: 140
A6: Bear ($) | B6: 107
A7: Cons EPS — Q+1e | B7: 0.37
A8: Cons EPS — Q+2e | B8: 0.14
A9: NTM EPS (approx = 2×(B7+B8)) | B9: =2*(B7+B8)
A10: P/E at current price | B10: =IF($B$9<=0,"n/m",B4/$B$9)
A11: P/E implied at PT | B11: =IF($B$9<=0,"n/m",B5/$B$9)
A12: P/E implied at bear | B12: =IF($B$9<=0,"n/m",B6/$B$9)
A13: Stated multiple anchor | B13: —
A14: Required NTM EPS for PT at stated mult | B14: —
A15: Consensus NTM vs required (gap) | B15: —
A16: Asymmetry (PT−P)/(P−bear) | B16: =(B5-B4)/(B4-B6)
A18: Methodology (as logged in Decisions Log / note):
A19: Scenario framework (6/19); consensus-aligned ($140 vs street avg $137.86)
A21: Implied price grid — NTM EPS (rows) × multiple (cols). All formulas.
A22: EPS \ Mult | B22: =IF(ISNUMBER(B12),ROUND(B12,1),ROUND(B10*0.7,1)) | C22: =ROUND(B10,1) | D22: =ROUND(B11,1)
A23: =ROUND($B$9*0.85,2) | B23: =$A23*B$22 | C23: =$A23*C$22 | D23: =$A23*D$22
A24: =ROUND($B$9*1,2) | B24: =$A24*B$22 | C24: =$A24*C$22 | D24: =$A24*D$22
A25: =ROUND($B$9*1.15,2) | B25: =$A25*B$22 | C25: =$A25*C$22 | D25: =$A25*D$22
A27: Audit note:
A28: ⚠️ Bear $107 ABOVE price — bear stale after −13% drawdown; refresh at Jul 31

Sheet CLS
A1: CLS — PT Audit Model (EPS × multiple) — Buy
A2: Built 2026-07-07 (evening). Consensus: Robinhood quarterly estimates 7/7 (next two quarters; NTM = 2 × sum — approximation, refine as quarters print). Prices: FMP official closes 7/7. Blue = input, Black = formula.
A4: Current price ($) | B4: 345.06
A5: Our PT ($) | B5: 530
A6: Bear ($) | B6: 250
A7: Cons EPS — Q+1e | B7: 2.27
A8: Cons EPS — Q+2e | B8: 2.65
A9: NTM EPS (approx = 2×(B7+B8)) | B9: =2*(B7+B8)
A10: P/E at current price | B10: =IF($B$9<=0,"n/m",B4/$B$9)
A11: P/E implied at PT | B11: =IF($B$9<=0,"n/m",B5/$B$9)
A12: P/E implied at bear | B12: =IF($B$9<=0,"n/m",B6/$B$9)
A13: Stated multiple anchor | B13: 54 | C13: Retro-documented 7/7 = implied P/E@PT (baseline for drift tracking)
A14: Required NTM EPS for PT at stated mult | B14: =IF(ISNUMBER(B13),B5/B13,"—")
A15: Consensus NTM vs required (gap) | B15: =IF(AND(ISNUMBER(B14),ISNUMBER(B9),B9>0),B9/B14-1,"—")
A16: Asymmetry (PT−P)/(P−bear) | B16: =(B5-B4)/(B4-B6)
A18: Methodology (as logged in Decisions Log / note):
A19: June-3 batch rating — no logged multiple anchor (Lesson #2 cohort)
A21: Implied price grid — NTM EPS (rows) × multiple (cols). All formulas.
A22: EPS \ Mult | B22: =IF(ISNUMBER(B12),ROUND(B12,1),ROUND(B10*0.7,1)) | C22: =ROUND(B10,1) | D22: =ROUND(B11,1)
A23: =ROUND($B$9*0.85,2) | B23: =$A23*B$22 | C23: =$A23*C$22 | D23: =$A23*D$22
A24: =ROUND($B$9*1,2) | B24: =$A24*B$22 | C24: =$A24*C$22 | D24: =$A24*D$22
A25: =ROUND($B$9*1.15,2) | B25: =$A25*B$22 | C25: =$A25*C$22 | D25: =$A25*D$22
A27: Audit note:
A28: June-3 batch PT — anchor undocumented

Sheet DLR
A1: DLR — PT Audit Model (EPS × multiple) — Buy
A2: Built 2026-07-07 (evening). Consensus: Robinhood quarterly estimates 7/7 (next two quarters; NTM = 2 × sum — approximation, refine as quarters print). Prices: FMP official closes 7/7. Blue = input, Black = formula.
A4: Current price ($) | B4: 174.9
A5: Our PT ($) | B5: 205
A6: Bear ($) | B6: 140
A7: Cons EPS — Q+1e | B7: 1.98
A8: Cons EPS — Q+2e | B8: 2
A9: NTM EPS (approx = 2×(B7+B8)) | B9: =2*(B7+B8)
A10: P/E at current price | B10: =IF($B$9<=0,"n/m",B4/$B$9)
A11: P/E implied at PT | B11: =IF($B$9<=0,"n/m",B5/$B$9)
A12: P/E implied at bear | B12: =IF($B$9<=0,"n/m",B6/$B$9)
A13: Stated multiple anchor | B13: 26 | C13: Retro-documented 7/7 = implied P/E@PT (baseline for drift tracking)
A14: Required NTM EPS for PT at stated mult | B14: =IF(ISNUMBER(B13),B5/B13,"—")
A15: Consensus NTM vs required (gap) | B15: =IF(AND(ISNUMBER(B14),ISNUMBER(B9),B9>0),B9/B14-1,"—")
A16: Asymmetry (PT−P)/(P−bear) | B16: =(B5-B4)/(B4-B6)
A18: Methodology (as logged in Decisions Log / note):
A19: June-3 batch rating — no logged multiple anchor (Lesson #2 cohort)
A21: Implied price grid — NTM EPS (rows) × multiple (cols). All formulas.
A22: EPS \ Mult | B22: =IF(ISNUMBER(B12),ROUND(B12,1),ROUND(B10*0.7,1)) | C22: =ROUND(B10,1) | D22: =ROUND(B11,1)
A23: =ROUND($B$9*0.85,2) | B23: =$A23*B$22 | C23: =$A23*C$22 | D23: =$A23*D$22
A24: =ROUND($B$9*1,2) | B24: =$A24*B$22 | C24: =$A24*C$22 | D24: =$A24*D$22
A25: =ROUND($B$9*1.15,2) | B25: =$A25*B$22 | C25: =$A25*C$22 | D25: =$A25*D$22
A27: Audit note:
A28: REIT — estimates are core-FFO-adjacent; P/E view approximate

Sheet FN
A1: FN — PT Audit Model (EPS × multiple) — Buy
A2: Built 2026-07-07 (evening). Consensus: Robinhood quarterly estimates 7/7 (next two quarters; NTM = 2 × sum — approximation, refine as quarters print). Prices: FMP official closes 7/7. Blue = input, Black = formula.
A4: Current price ($) | B4: 468.48
A5: Our PT ($) | B5: 720
A6: Bear ($) | B6: 450
A7: Cons EPS — Q+1e | B7: 3.78
A8: Cons EPS — Q+2e | B8: 3.94
A9: NTM EPS (approx = 2×(B7+B8)) | B9: =2*(B7+B8)
A10: P/E at current price | B10: =IF($B$9<=0,"n/m",B4/$B$9)
A11: P/E implied at PT | B11: =IF($B$9<=0,"n/m",B5/$B$9)
A12: P/E implied at bear | B12: =IF($B$9<=0,"n/m",B6/$B$9)
A13: Stated multiple anchor | B13: 47 | C13: Retro-documented 7/7 = implied P/E@PT (baseline for drift tracking)
A14: Required NTM EPS for PT at stated mult | B14: =IF(ISNUMBER(B13),B5/B13,"—")
A15: Consensus NTM vs required (gap) | B15: =IF(AND(ISNUMBER(B14),ISNUMBER(B9),B9>0),B9/B14-1,"—")
A16: Asymmetry (PT−P)/(P−bear) | B16: =(B5-B4)/(B4-B6)
A18: Methodology (as logged in Decisions Log / note):
A19: June-3 batch rating — no logged multiple anchor (Lesson #2 cohort)
A21: Implied price grid — NTM EPS (rows) × multiple (cols). All formulas.
A22: EPS \ Mult | B22: =IF(ISNUMBER(B12),ROUND(B12,1),ROUND(B10*0.7,1)) | C22: =ROUND(B10,1) | D22: =ROUND(B11,1)
A23: =ROUND($B$9*0.85,2) | B23: =$A23*B$22 | C23: =$A23*C$22 | D23: =$A23*D$22
A24: =ROUND($B$9*1,2) | B24: =$A24*B$22 | C24: =$A24*C$22 | D24: =$A24*D$22
A25: =ROUND($B$9*1.15,2) | B25: =$A25*B$22 | C25: =$A25*C$22 | D25: =$A25*D$22
A27: Audit note:
A28: June-3 batch PT — anchor undocumented

Sheet GNRC
A1: GNRC — PT Audit Model (EPS × multiple) — Buy
A2: Built 2026-07-07 (evening). Consensus: Robinhood quarterly estimates 7/7 (next two quarters; NTM = 2 × sum — approximation, refine as quarters print). Prices: FMP official closes 7/7. Blue = input, Black = formula.
A4: Current price ($) | B4: 235.8
A5: Our PT ($) | B5: 320
A6: Bear ($) | B6: 175
A7: Cons EPS — Q+1e | B7: 1.99
A8: Cons EPS — Q+2e | B8: 2.55
A9: NTM EPS (approx = 2×(B7+B8)) | B9: =2*(B7+B8)
A10: P/E at current price | B10: =IF($B$9<=0,"n/m",B4/$B$9)
A11: P/E implied at PT | B11: =IF($B$9<=0,"n/m",B5/$B$9)
A12: P/E implied at bear | B12: =IF($B$9<=0,"n/m",B6/$B$9)
A13: Stated multiple anchor | B13: 35 | C13: Retro-documented 7/7 = implied P/E@PT (baseline for drift tracking)
A14: Required NTM EPS for PT at stated mult | B14: =IF(ISNUMBER(B13),B5/B13,"—")
A15: Consensus NTM vs required (gap) | B15: =IF(AND(ISNUMBER(B14),ISNUMBER(B9),B9>0),B9/B14-1,"—")
A16: Asymmetry (PT−P)/(P−bear) | B16: =(B5-B4)/(B4-B6)
A18: Methodology (as logged in Decisions Log / note):
A19: June-3 batch rating (screener); backlog-visibility cohort per Lesson #1
A21: Implied price grid — NTM EPS (rows) × multiple (cols). All formulas.
A22: EPS \ Mult | B22: =IF(ISNUMBER(B12),ROUND(B12,1),ROUND(B10*0.7,1)) | C22: =ROUND(B10,1) | D22: =ROUND(B11,1)
A23: =ROUND($B$9*0.85,2) | B23: =$A23*B$22 | C23: =$A23*C$22 | D23: =$A23*D$22
A24: =ROUND($B$9*1,2) | B24: =$A24*B$22 | C24: =$A24*C$22 | D24: =$A24*D$22
A25: =ROUND($B$9*1.15,2) | B25: =$A25*B$22 | C25: =$A25*C$22 | D25: =$A25*D$22
A27: Audit note:
A28: June-3 batch PT — anchor undocumented

Sheet HUBB
A1: HUBB — PT Audit Model (EPS × multiple) — Buy
A2: Built 2026-07-07 (evening). Consensus: Robinhood quarterly estimates 7/7 (next two quarters; NTM = 2 × sum — approximation, refine as quarters print). Prices: FMP official closes 7/7. Blue = input, Black = formula.
A4: Current price ($) | B4: 478.89
A5: Our PT ($) | B5: 545
A6: Bear ($) | B6: 320
A7: Cons EPS — Q+1e | B7: 5.4
A8: Cons EPS — Q+2e | B8: 5.59
A9: NTM EPS (approx = 2×(B7+B8)) | B9: =2*(B7+B8)
A10: P/E at current price | B10: =IF($B$9<=0,"n/m",B4/$B$9)
A11: P/E implied at PT | B11: =IF($B$9<=0,"n/m",B5/$B$9)
A12: P/E implied at bear | B12: =IF($B$9<=0,"n/m",B6/$B$9)
A13: Stated multiple anchor | B13: 25 | C13: Retro-documented 7/7 = implied P/E@PT (baseline for drift tracking)
A14: Required NTM EPS for PT at stated mult | B14: =IF(ISNUMBER(B13),B5/B13,"—")
A15: Consensus NTM vs required (gap) | B15: =IF(AND(ISNUMBER(B14),ISNUMBER(B9),B9>0),B9/B14-1,"—")
A16: Asymmetry (PT−P)/(P−bear) | B16: =(B5-B4)/(B4-B6)
A18: Methodology (as logged in Decisions Log / note):
A19: June-3 batch rating; brief 6/? (HUBB_brief)
A21: Implied price grid — NTM EPS (rows) × multiple (cols). All formulas.
A22: EPS \ Mult | B22: =IF(ISNUMBER(B12),ROUND(B12,1),ROUND(B10*0.7,1)) | C22: =ROUND(B10,1) | D22: =ROUND(B11,1)
A23: =ROUND($B$9*0.85,2) | B23: =$A23*B$22 | C23: =$A23*C$22 | D23: =$A23*D$22
A24: =ROUND($B$9*1,2) | B24: =$A24*B$22 | C24: =$A24*C$22 | D24: =$A24*D$22
A25: =ROUND($B$9*1.15,2) | B25: =$A25*B$22 | C25: =$A25*C$22 | D25: =$A25*D$22
A27: Audit note:
A28: June-3 batch PT — anchor undocumented

Sheet IRM
A1: IRM — PT Audit Model (EPS × multiple) — Buy
A2: Built 2026-07-07 (evening). Consensus: Robinhood quarterly estimates 7/7 (next two quarters; NTM = 2 × sum — approximation, refine as quarters print). Prices: FMP official closes 7/7. Blue = input, Black = formula.
A4: Current price ($) | B4: 115.75
A5: Our PT ($) | B5: 145
A6: Bear ($) | B6: 100
A7: Cons EPS — Q+1e | B7: 1.28
A8: Cons EPS — Q+2e | B8: 1.35
A9: NTM EPS (approx = 2×(B7+B8)) | B9: =2*(B7+B8)
A10: P/E at current price | B10: =IF($B$9<=0,"n/m",B4/$B$9)
A11: P/E implied at PT | B11: =IF($B$9<=0,"n/m",B5/$B$9)
A12: P/E implied at bear | B12: =IF($B$9<=0,"n/m",B6/$B$9)
A13: Stated multiple anchor | B13: 28 | C13: Retro-documented 7/7 = implied P/E@PT (baseline for drift tracking)
A14: Required NTM EPS for PT at stated mult | B14: =IF(ISNUMBER(B13),B5/B13,"—")
A15: Consensus NTM vs required (gap) | B15: =IF(AND(ISNUMBER(B14),ISNUMBER(B9),B9>0),B9/B14-1,"—")
A16: Asymmetry (PT−P)/(P−bear) | B16: =(B5-B4)/(B4-B6)
A18: Methodology (as logged in Decisions Log / note):
A19: June-3 batch rating — no logged multiple anchor (Lesson #2 cohort)
A21: Implied price grid — NTM EPS (rows) × multiple (cols). All formulas.
A22: EPS \ Mult | B22: =IF(ISNUMBER(B12),ROUND(B12,1),ROUND(B10*0.7,1)) | C22: =ROUND(B10,1) | D22: =ROUND(B11,1)
A23: =ROUND($B$9*0.85,2) | B23: =$A23*B$22 | C23: =$A23*C$22 | D23: =$A23*D$22
A24: =ROUND($B$9*1,2) | B24: =$A24*B$22 | C24: =$A24*C$22 | D24: =$A24*D$22
A25: =ROUND($B$9*1.15,2) | B25: =$A25*B$22 | C25: =$A25*C$22 | D25: =$A25*D$22
A27: Audit note:
A28: REIT — estimates are AFFO-adjacent; P/E view approximate

Sheet LITE
A1: LITE — PT Audit Model (EPS × multiple) — Buy
A2: Built 2026-07-07 (evening). Consensus: Robinhood quarterly estimates 7/7 (next two quarters; NTM = 2 × sum — approximation, refine as quarters print). Prices: FMP official closes 7/7. Blue = input, Black = formula.
A4: Current price ($) | B4: 698.91
A5: Our PT ($) | B5: 1150
A6: Bear ($) | B6: 600
A7: Cons EPS — Q+1e | B7: 2.89
A8: Cons EPS — Q+2e | B8: 3.51
A9: NTM EPS (approx = 2×(B7+B8)) | B9: =2*(B7+B8)
A10: P/E at current price | B10: =IF($B$9<=0,"n/m",B4/$B$9)
A11: P/E implied at PT | B11: =IF($B$9<=0,"n/m",B5/$B$9)
A12: P/E implied at bear | B12: =IF($B$9<=0,"n/m",B6/$B$9)
A13: Stated multiple anchor | B13: —
A14: Required NTM EPS for PT at stated mult | B14: —
A15: Consensus NTM vs required (gap) | B15: —
A16: Asymmetry (PT−P)/(P−bear) | B16: =(B5-B4)/(B4-B6)
A18: Methodology (as logged in Decisions Log / note):
A19: ~14x NTM revenue (AI optical premium)
A21: Implied price grid — NTM EPS (rows) × multiple (cols). All formulas.
A22: EPS \ Mult | B22: =IF(ISNUMBER(B12),ROUND(B12,1),ROUND(B10*0.7,1)) | C22: =ROUND(B10,1) | D22: =ROUND(B11,1)
A23: =ROUND($B$9*0.85,2) | B23: =$A23*B$22 | C23: =$A23*C$22 | D23: =$A23*D$22
A24: =ROUND($B$9*1,2) | B24: =$A24*B$22 | C24: =$A24*C$22 | D24: =$A24*D$22
A25: =ROUND($B$9*1.15,2) | B25: =$A25*B$22 | C25: =$A25*C$22 | D25: =$A25*D$22
A27: Audit note:
A28: Revenue-multiple anchor; P/E secondary

Sheet MOD
A1: MOD — PT Audit Model (EPS × multiple) — Buy
A2: Built 2026-07-07 (evening). Consensus: Robinhood quarterly estimates 7/7 (next two quarters; NTM = 2 × sum — approximation, refine as quarters print). Prices: FMP official closes 7/7. Blue = input, Black = formula.
A4: Current price ($) | B4: 230.41
A5: Our PT ($) | B5: 355
A6: Bear ($) | B6: 150
A7: Cons EPS — Q+1e | B7: 1.38
A8: Cons EPS — Q+2e | B8: 1.77
A9: NTM EPS (approx = 2×(B7+B8)) | B9: =2*(B7+B8)
A10: P/E at current price | B10: =IF($B$9<=0,"n/m",B4/$B$9)
A11: P/E implied at PT | B11: =IF($B$9<=0,"n/m",B5/$B$9)
A12: P/E implied at bear | B12: =IF($B$9<=0,"n/m",B6/$B$9)
A13: Stated multiple anchor | B13: 56 | C13: Retro-documented 7/7 = implied P/E@PT (baseline for drift tracking)
A14: Required NTM EPS for PT at stated mult | B14: =IF(ISNUMBER(B13),B5/B13,"—")
A15: Consensus NTM vs required (gap) | B15: =IF(AND(ISNUMBER(B14),ISNUMBER(B9),B9>0),B9/B14-1,"—")
A16: Asymmetry (PT−P)/(P−bear) | B16: =(B5-B4)/(B4-B6)
A18: Methodology (as logged in Decisions Log / note):
A19: June-3 batch rating — no logged multiple anchor (Lesson #2 cohort)
A21: Implied price grid — NTM EPS (rows) × multiple (cols). All formulas.
A22: EPS \ Mult | B22: =IF(ISNUMBER(B12),ROUND(B12,1),ROUND(B10*0.7,1)) | C22: =ROUND(B10,1) | D22: =ROUND(B11,1)
A23: =ROUND($B$9*0.85,2) | B23: =$A23*B$22 | C23: =$A23*C$22 | D23: =$A23*D$22
A24: =ROUND($B$9*1,2) | B24: =$A24*B$22 | C24: =$A24*C$22 | D24: =$A24*D$22
A25: =ROUND($B$9*1.15,2) | B25: =$A25*B$22 | C25: =$A25*C$22 | D25: =$A25*D$22
A27: Audit note:
A28: June-3 batch PT — anchor undocumented

Sheet MP
A1: MP — PT Audit Model (EPS × multiple) — Buy
A2: Built 2026-07-07 (evening). Consensus: Robinhood quarterly estimates 7/7 (next two quarters; NTM = 2 × sum — approximation, refine as quarters print). Prices: FMP official closes 7/7. Blue = input, Black = formula.
A4: Current price ($) | B4: 50.49
A5: Our PT ($) | B5: 80
A6: Bear ($) | B6: 35
A7: Cons EPS — Q+1e | B7: 0.02
A8: Cons EPS — Q+2e | B8: 0.06
A9: NTM EPS (approx = 2×(B7+B8)) | B9: =2*(B7+B8)
A10: P/E at current price | B10: =IF($B$9<=0,"n/m",B4/$B$9)
A11: P/E implied at PT | B11: =IF($B$9<=0,"n/m",B5/$B$9)
A12: P/E implied at bear | B12: =IF($B$9<=0,"n/m",B6/$B$9)
A13: Stated multiple anchor | B13: —
A14: Required NTM EPS for PT at stated mult | B14: —
A15: Consensus NTM vs required (gap) | B15: —
A16: Asymmetry (PT−P)/(P−bear) | B16: =(B5-B4)/(B4-B6)
A18: Methodology (as logged in Decisions Log / note):
A19: Thesis-driven (rare-earth strategic value)
A21: Implied price grid — NTM EPS (rows) × multiple (cols). All formulas.
A22: EPS \ Mult | B22: =IF(ISNUMBER(B12),ROUND(B12,1),ROUND(B10*0.7,1)) | C22: =ROUND(B10,1) | D22: =ROUND(B11,1)
A23: =ROUND($B$9*0.85,2) | B23: =$A23*B$22 | C23: =$A23*C$22 | D23: =$A23*D$22
A24: =ROUND($B$9*1,2) | B24: =$A24*B$22 | C24: =$A24*C$22 | D24: =$A24*D$22
A25: =ROUND($B$9*1.15,2) | B25: =$A25*B$22 | C25: =$A25*C$22 | D25: =$A25*D$22
A27: Audit note:
A28: Near-zero EPS — P/E distorted; strategic-asset framework
A31: REVENUE FRAMEWORK (added 7/7 evening — EPS-negative/near-zero name)
A32: Vault anchors used (consensus revenue unavailable on current data plan); audit = growth embedded in the PT.
A33: Market cap 7/7 ($B) | B33: 8.988
A34: Net debt ($B) | B34: 1
A35: Vault revenue anchor (EV/Rev x) | B35: 7
A36: Run-rate revenue ($B) | B36: 0.224 | C36: note run-rate $224M
A37: Cap @ PT ($B) | B37: =B33*B5/B4
A38: EV @ PT ($B) | B38: =B37+IF(ISNUMBER(B34),B34,0)
A39: Implied NTM revenue the PT requires ($B) | B39: =IF(ISNUMBER(B35),B38/B35,"—")
A40: Growth embedded: implied rev ÷ run-rate | B40: =IF(AND(ISNUMBER(B39),ISNUMBER(B36)),B39/B36,"—")
A41: P/S at price (run-rate) | B41: =IF(ISNUMBER(B36),B33/B36,"—")
A43: Note:
A44: EV/Rev 7x anchor. Net debt ≈ $999M debt, cash [VERIFY].

Sheet MRVL
A1: MRVL — PT Audit Model (EPS × multiple) — Buy
A2: Built 2026-07-07 (evening). Consensus: Robinhood quarterly estimates 7/7 (next two quarters; NTM = 2 × sum — approximation, refine as quarters print). Prices: FMP official closes 7/7. Blue = input, Black = formula.
A4: Current price ($) | B4: 230.7
A5: Our PT ($) | B5: 370
A6: Bear ($) | B6: 180
A7: Cons EPS — Q+1e | B7: 0.87
A8: Cons EPS — Q+2e | B8: 1.02
A9: NTM EPS (approx = 2×(B7+B8)) | B9: =2*(B7+B8)
A10: P/E at current price | B10: =IF($B$9<=0,"n/m",B4/$B$9)
A11: P/E implied at PT | B11: =IF($B$9<=0,"n/m",B5/$B$9)
A12: P/E implied at bear | B12: =IF($B$9<=0,"n/m",B6/$B$9)
A13: Stated multiple anchor | B13: —
A14: Required NTM EPS for PT at stated mult | B14: —
A15: Consensus NTM vs required (gap) | B15: —
A16: Asymmetry (PT−P)/(P−bear) | B16: =(B5-B4)/(B4-B6)
A18: Methodology (as logged in Decisions Log / note):
A19: Thesis-driven (custom ASIC #2)
A21: Implied price grid — NTM EPS (rows) × multiple (cols). All formulas.
A22: EPS \ Mult | B22: =IF(ISNUMBER(B12),ROUND(B12,1),ROUND(B10*0.7,1)) | C22: =ROUND(B10,1) | D22: =ROUND(B11,1)
A23: =ROUND($B$9*0.85,2) | B23: =$A23*B$22 | C23: =$A23*C$22 | D23: =$A23*D$22
A24: =ROUND($B$9*1,2) | B24: =$A24*B$22 | C24: =$A24*C$22 | D24: =$A24*D$22
A25: =ROUND($B$9*1.15,2) | B25: =$A25*B$22 | C25: =$A25*C$22 | D25: =$A25*D$22
A27: Audit note:
A28: Queued from top-10 pass; anchor undocumented

Sheet NBIS
A1: NBIS — PT Audit Model (EPS × multiple) — Buy
A2: Built 2026-07-07 (evening). Consensus: Robinhood quarterly estimates 7/7 (next two quarters; NTM = 2 × sum — approximation, refine as quarters print). Prices: FMP official closes 7/7. Blue = input, Black = formula.
A4: Current price ($) | B4: 195.19
A5: Our PT ($) | B5: 310
A6: Bear ($) | B6: 80
A7: Cons EPS — Q+1e | B7: -0.73
A8: Cons EPS — Q+2e | B8: -1.03
A9: NTM EPS (approx = 2×(B7+B8)) | B9: =2*(B7+B8)
A10: P/E at current price | B10: =IF($B$9<=0,"n/m",B4/$B$9)
A11: P/E implied at PT | B11: =IF($B$9<=0,"n/m",B5/$B$9)
A12: P/E implied at bear | B12: =IF($B$9<=0,"n/m",B6/$B$9)
A13: Stated multiple anchor | B13: —
A14: Required NTM EPS for PT at stated mult | B14: —
A15: Consensus NTM vs required (gap) | B15: —
A16: Asymmetry (PT−P)/(P−bear) | B16: =(B5-B4)/(B4-B6)
A18: Methodology (as logged in Decisions Log / note):
A19: ~10x NTM revenue — highest-growth name (+529% YoY)
A21: Grid omitted — EPS-negative / derived-price name; P/E framework not meaningful.
A27: Audit note:
A28: EPS-negative — revenue-multiple name; P/E n/a
A31: REVENUE FRAMEWORK (added 7/7 evening — EPS-negative/near-zero name)
A32: Vault anchors used (consensus revenue unavailable on current data plan); audit = growth embedded in the PT.
A33: Market cap 7/7 ($B) | B33: 46.846
A34: Net debt ($B) | B34: 0
A35: Vault revenue anchor (EV/Rev x) | B35: 10
A36: Run-rate revenue ($B) | B36: 1.6 | C36: Q1'26 $399M × 4 (+684% YoY)
A37: Cap @ PT ($B) | B37: =B33*B5/B4
A38: EV @ PT ($B) | B38: =B37+IF(ISNUMBER(B34),B34,0)
A39: Implied NTM revenue the PT requires ($B) | B39: =IF(ISNUMBER(B35),B38/B35,"—")
A40: Growth embedded: implied rev ÷ run-rate | B40: =IF(AND(ISNUMBER(B39),ISNUMBER(B36)),B39/B36,"—")
A41: P/S at price (run-rate) | B41: =IF(ISNUMBER(B36),B33/B36,"—")
A43: Note:
A44: EV/Rev 10x anchor. Net debt ~0 assumed [VERIFY].

Sheet SPXC
A1: SPXC — PT Audit Model (EPS × multiple) — Buy
A2: Built 2026-07-07 (evening). Consensus: Robinhood quarterly estimates 7/7 (next two quarters; NTM = 2 × sum — approximation, refine as quarters print). Prices: FMP official closes 7/7. Blue = input, Black = formula.
A4: Current price ($) | B4: 218.83
A5: Our PT ($) | B5: 250
A6: Bear ($) | B6: 150
A7: Cons EPS — Q+1e | B7: 1.85
A8: Cons EPS — Q+2e | B8: 2.1
A9: NTM EPS (approx = 2×(B7+B8)) | B9: =2*(B7+B8)
A10: P/E at current price | B10: =IF($B$9<=0,"n/m",B4/$B$9)
A11: P/E implied at PT | B11: =IF($B$9<=0,"n/m",B5/$B$9)
A12: P/E implied at bear | B12: =IF($B$9<=0,"n/m",B6/$B$9)
A13: Stated multiple anchor | B13: 32 | C13: Retro-documented 7/7 = implied P/E@PT (baseline for drift tracking)
A14: Required NTM EPS for PT at stated mult | B14: =IF(ISNUMBER(B13),B5/B13,"—")
A15: Consensus NTM vs required (gap) | B15: =IF(AND(ISNUMBER(B14),ISNUMBER(B9),B9>0),B9/B14-1,"—")
A16: Asymmetry (PT−P)/(P−bear) | B16: =(B5-B4)/(B4-B6)
A18: Methodology (as logged in Decisions Log / note):
A19: June-3 batch rating — no logged multiple anchor (Lesson #2 cohort)
A21: Implied price grid — NTM EPS (rows) × multiple (cols). All formulas.
A22: EPS \ Mult | B22: =IF(ISNUMBER(B12),ROUND(B12,1),ROUND(B10*0.7,1)) | C22: =ROUND(B10,1) | D22: =ROUND(B11,1)
A23: =ROUND($B$9*0.85,2) | B23: =$A23*B$22 | C23: =$A23*C$22 | D23: =$A23*D$22
A24: =ROUND($B$9*1,2) | B24: =$A24*B$22 | C24: =$A24*C$22 | D24: =$A24*D$22
A25: =ROUND($B$9*1.15,2) | B25: =$A25*B$22 | C25: =$A25*C$22 | D25: =$A25*D$22
A27: Audit note:
A28: June-3 batch PT — anchor undocumented

Sheet UUUU
A1: UUUU — PT Audit Model — Hold (Speculative), PT SUSPENDED 7/7
A2: Built 2026-07-07 (evening). Consensus: Robinhood quarterly estimates 7/7 (next two quarters; NTM = 2 × sum — approximation, refine as quarters print). Prices: FMP official closes 7/7. Blue = input, Black = formula.
A4: Current price ($) | B4: 12.86
A5: Our PT ($) | B5: 25
A6: Bear ($) | B6: 4
A7: Cons EPS — Q+1e | B7: -0.04
A8: Cons EPS — Q+2e | B8: -0.03
A9: NTM EPS (approx = 2×(B7+B8)) | B9: =2*(B7+B8)
A10: P/E at current price | B10: =IF($B$9<=0,"n/m",B4/$B$9)
A11: P/E implied at PT | B11: =IF($B$9<=0,"n/m",B5/$B$9)
A12: P/E implied at bear | B12: =IF($B$9<=0,"n/m",B6/$B$9)
A13: Stated multiple anchor | B13: —
A14: Required NTM EPS for PT at stated mult | B14: —
A15: Consensus NTM vs required (gap) | B15: —
A16: Asymmetry (PT−P)/(P−bear) | B16: =(B5-B4)/(B4-B6)
A18: Methodology (as logged in Decisions Log / note):
A19: Thesis-driven (uranium + REE optionality)
A21: Grid omitted — EPS-negative / derived-price name; P/E framework not meaningful.
A27: Audit note:
A28: PT $25 SUSPENDED 7/7 evening (this audit was the trigger): 5x anchor implies ~$1.37B NTM rev vs $66M FY2025 = 21x embedded growth. Downgraded Buy→Hold (Speculative), no PT. Bear $4 retained. See Decisions Log 7/7 + UUUU.md re-underwrite section. B5 kept for reference only — do not cite $25.
A31: REVENUE FRAMEWORK (added 7/7 evening — EPS-negative/near-zero name)
A32: Vault anchors used (consensus revenue unavailable on current data plan); audit = growth embedded in the PT.
A33: Market cap 7/7 ($B) | B33: 3.213
A34: Net debt ($B) | B34: 0.589
A35: Vault revenue anchor (EV/Rev x) | B35: 5
A36: Run-rate revenue ($B) | B36: 0.066 | C36: FY2025 actual $66M (−15% YoY)
A37: Cap @ PT ($B) | B37: =B33*B5/B4
A38: EV @ PT ($B) | B38: =B37+IF(ISNUMBER(B34),B34,0)
A39: Implied NTM revenue the PT requires ($B) | B39: =IF(ISNUMBER(B35),B38/B35,"—")
A40: Growth embedded: implied rev ÷ run-rate | B40: =IF(AND(ISNUMBER(B39),ISNUMBER(B36)),B39/B36,"—")
A41: P/S at price (run-rate) | B41: =IF(ISNUMBER(B36),B33/B36,"—")
A43: Note:
A44: EV/Rev 5x anchor. Net debt = $676M debt − $87M cash [VERIFY].

Sheet XYL
A1: XYL — PT Audit Model (EPS × multiple) — Buy
A2: Built 2026-07-07 (evening). Consensus: Robinhood quarterly estimates 7/7 (next two quarters; NTM = 2 × sum — approximation, refine as quarters print). Prices: FMP official closes 7/7. Blue = input, Black = formula.
A4: Current price ($) | B4: 120.65
A5: Our PT ($) | B5: 135
A6: Bear ($) | B6: 85
A7: Cons EPS — Q+1e | B7: 1.34
A8: Cons EPS — Q+2e | B8: 1.46
A9: NTM EPS (approx = 2×(B7+B8)) | B9: =2*(B7+B8)
A10: P/E at current price | B10: =IF($B$9<=0,"n/m",B4/$B$9)
A11: P/E implied at PT | B11: =IF($B$9<=0,"n/m",B5/$B$9)
A12: P/E implied at bear | B12: =IF($B$9<=0,"n/m",B6/$B$9)
A13: Stated multiple anchor | B13: —
A14: Required NTM EPS for PT at stated mult | B14: —
A15: Consensus NTM vs required (gap) | B15: —
A16: Asymmetry (PT−P)/(P−bear) | B16: =(B5-B4)/(B4-B6)
A18: Methodology (as logged in Decisions Log / note):
A19: Screener (water as DC bottleneck)
A21: Implied price grid — NTM EPS (rows) × multiple (cols). All formulas.
A22: EPS \ Mult | B22: =IF(ISNUMBER(B12),ROUND(B12,1),ROUND(B10*0.7,1)) | C22: =ROUND(B10,1) | D22: =ROUND(B11,1)
A23: =ROUND($B$9*0.85,2) | B23: =$A23*B$22 | C23: =$A23*C$22 | D23: =$A23*D$22
A24: =ROUND($B$9*1,2) | B24: =$A24*B$22 | C24: =$A24*C$22 | D24: =$A24*D$22
A25: =ROUND($B$9*1.15,2) | B25: =$A25*B$22 | C25: =$A25*C$22 | D25: =$A25*D$22
A27: Audit note:
A28: Clean

Sheet ASML
A1: ASML — PT Audit Model (EPS × multiple) — Hold
A2: Built 2026-07-07 (evening). Consensus: Robinhood quarterly estimates 7/7 (next two quarters; NTM = 2 × sum — approximation, refine as quarters print). Prices: FMP official closes 7/7. Blue = input, Black = formula.
A4: Current price ($) | B4: 1747.28
A5: Our PT ($) | B5: 1730
A6: Bear ($) | B6: —
A7: Cons EPS — Q+1e | B7: 7.98
A8: Cons EPS — Q+2e | B8: 9.14
A9: NTM EPS (approx = 2×(B7+B8)) | B9: =2*(B7+B8)
A10: P/E at current price | B10: =IF($B$9<=0,"n/m",B4/$B$9)
A11: P/E implied at PT | B11: =IF($B$9<=0,"n/m",B5/$B$9)
A12: P/E implied at bear | B12: —
A13: Stated multiple anchor | B13: —
A14: Required NTM EPS for PT at stated mult | B14: —
A15: Consensus NTM vs required (gap) | B15: —
A16: Asymmetry (PT−P)/(P−bear) | B16: — (no bear logged)
A18: Methodology (as logged in Decisions Log / note):
A19: PT STALE — ratified PT-reset event; all Jul 15 branches fire a PT action
A21: Implied price grid — NTM EPS (rows) × multiple (cols). All formulas.
A22: EPS \ Mult | B22: =IF(ISNUMBER(B12),ROUND(B12,1),ROUND(B10*0.7,1)) | C22: =ROUND(B10,1) | D22: =ROUND(B11,1)
A23: =ROUND($B$9*0.85,2) | B23: =$A23*B$22 | C23: =$A23*C$22 | D23: =$A23*D$22
A24: =ROUND($B$9*1,2) | B24: =$A24*B$22 | C24: =$A24*C$22 | D24: =$A24*D$22
A25: =ROUND($B$9*1.15,2) | B25: =$A25*B$22 | C25: =$A25*C$22 | D25: =$A25*D$22
A27: Audit note:
A28: ⚠️ PT stale + no bear — BOTH set at Jul 15 reset. Price back above stale PT

Sheet BW
A1: BW — PT Audit Model (EPS × multiple) — Hold
A2: Built 2026-07-07 (evening). Consensus: Robinhood quarterly estimates 7/7 (next two quarters; NTM = 2 × sum — approximation, refine as quarters print). Prices: FMP official closes 7/7. Blue = input, Black = formula.
A4: Current price ($) | B4: 10.73
A5: Our PT ($) | B5: 18
A6: Bear ($) | B6: 4
A7: Cons EPS — Q+1e | B7: 0.03
A8: Cons EPS — Q+2e | B8: 0.07
A9: NTM EPS (approx = 2×(B7+B8)) | B9: =2*(B7+B8)
A10: P/E at current price | B10: =IF($B$9<=0,"n/m",B4/$B$9)
A11: P/E implied at PT | B11: =IF($B$9<=0,"n/m",B5/$B$9)
A12: P/E implied at bear | B12: =IF($B$9<=0,"n/m",B6/$B$9)
A13: Stated multiple anchor | B13: —
A14: Required NTM EPS for PT at stated mult | B14: —
A15: Consensus NTM vs required (gap) | B15: —
A16: Asymmetry (PT−P)/(P−bear) | B16: =(B5-B4)/(B4-B6)
A18: Methodology (as logged in Decisions Log / note):
A19: 2.5–3x EV/Revenue on FY2026E ~$950M (6/29)
A21: Implied price grid — NTM EPS (rows) × multiple (cols). All formulas.
A22: EPS \ Mult | B22: =IF(ISNUMBER(B12),ROUND(B12,1),ROUND(B10*0.7,1)) | C22: =ROUND(B10,1) | D22: =ROUND(B11,1)
A23: =ROUND($B$9*0.85,2) | B23: =$A23*B$22 | C23: =$A23*C$22 | D23: =$A23*D$22
A24: =ROUND($B$9*1,2) | B24: =$A24*B$22 | C24: =$A24*C$22 | D24: =$A24*D$22
A25: =ROUND($B$9*1.15,2) | B25: =$A25*B$22 | C25: =$A25*C$22 | D25: =$A25*D$22
A27: Audit note:
A28: EV/Rev name; P/E distorted. Upgrade ≤$9 (16% away) or refi/2nd hyperscaler
A31: REVENUE FRAMEWORK (added 7/7 evening — EPS-negative/near-zero name)
A32: Vault anchors used (consensus revenue unavailable on current data plan); audit = growth embedded in the PT.
A33: Market cap 7/7 ($B) | B33: 1.227
A34: Net debt ($B) | B34: 0.3
A35: Vault revenue anchor (EV/Rev x) | B35: 2.75
A36: Run-rate revenue ($B) | B36: 0.95 | C36: FY2026E $950M (logged PT basis)
A37: Cap @ PT ($B) | B37: =B33*B5/B4
A38: EV @ PT ($B) | B38: =B37+IF(ISNUMBER(B34),B34,0)
A39: Implied NTM revenue the PT requires ($B) | B39: =IF(ISNUMBER(B35),B38/B35,"—")
A40: Growth embedded: implied rev ÷ run-rate | B40: =IF(AND(ISNUMBER(B39),ISNUMBER(B36)),B39/B36,"—")
A41: P/S at price (run-rate) | B41: =IF(ISNUMBER(B36),B33/B36,"—")
A43: Note:
A44: EV/Rev 2.5–3x anchor (midpoint 2.75x).

Sheet COHR
A1: COHR — PT Audit Model (EPS × multiple) — Hold
A2: Built 2026-07-07 (evening). Consensus: Robinhood quarterly estimates 7/7 (next two quarters; NTM = 2 × sum — approximation, refine as quarters print). Prices: FMP official closes 7/7. Blue = input, Black = formula.
A4: Current price ($) | B4: 314.13
A5: Our PT ($) | B5: 420
A6: Bear ($) | B6: 150 | C6: SCREENING bear set 7/7: 23x trough × cons NTM $6.62 — leverage discount to WFE peers — refine at print
A7: Cons EPS — Q+1e | B7: 1.58
A8: Cons EPS — Q+2e | B8: 1.73
A9: NTM EPS (approx = 2×(B7+B8)) | B9: =2*(B7+B8)
A10: P/E at current price | B10: =IF($B$9<=0,"n/m",B4/$B$9)
A11: P/E implied at PT | B11: =IF($B$9<=0,"n/m",B5/$B$9)
A12: P/E implied at bear | B12: =IF($B$9<=0,"n/m",B6/$B$9)
A13: Stated multiple anchor | B13: 63 | C13: Retro-documented 7/7 = implied P/E@PT (baseline for drift tracking)
A14: Required NTM EPS for PT at stated mult | B14: =IF(ISNUMBER(B13),B5/B13,"—")
A15: Consensus NTM vs required (gap) | B15: =IF(AND(ISNUMBER(B14),ISNUMBER(B9),B9>0),B9/B14-1,"—")
A16: Asymmetry (PT−P)/(P−bear) | B16: =(B5-B4)/(B4-B6)
A18: Methodology (as logged in Decisions Log / note):
A19: June-3 batch rating — no logged multiple anchor (Lesson #2 cohort)
A21: Implied price grid — NTM EPS (rows) × multiple (cols). All formulas.
A22: EPS \ Mult | B22: =IF(ISNUMBER(B12),ROUND(B12,1),ROUND(B10*0.7,1)) | C22: =ROUND(B10,1) | D22: =ROUND(B11,1)
A23: =ROUND($B$9*0.85,2) | B23: =$A23*B$22 | C23: =$A23*C$22 | D23: =$A23*D$22
A24: =ROUND($B$9*1,2) | B24: =$A24*B$22 | C24: =$A24*C$22 | D24: =$A24*D$22
A25: =ROUND($B$9*1.15,2) | B25: =$A25*B$22 | C25: =$A25*C$22 | D25: =$A25*D$22
A27: Audit note:
A28: ⚠️ No bear logged — asymmetry incomputable

Sheet CRDO
A1: CRDO — PT Audit Model (EPS × multiple) — Hold
A2: Built 2026-07-07 (evening). Consensus: Robinhood quarterly estimates 7/7 (next two quarters; NTM = 2 × sum — approximation, refine as quarters print). Prices: FMP official closes 7/7. Blue = input, Black = formula.
A4: Current price ($) | B4: 246.4
A5: Our PT ($) | B5: 250
A6: Bear ($) | B6: 120 | C6: SCREENING bear set 7/7: 26x growth-trough × cons NTM $4.58 — hyper-grower, premium retained at trough — refine at print
A7: Cons EPS — Q+1e | B7: 1.11
A8: Cons EPS — Q+2e | B8: 1.18
A9: NTM EPS (approx = 2×(B7+B8)) | B9: =2*(B7+B8)
A10: P/E at current price | B10: =IF($B$9<=0,"n/m",B4/$B$9)
A11: P/E implied at PT | B11: =IF($B$9<=0,"n/m",B5/$B$9)
A12: P/E implied at bear | B12: =IF($B$9<=0,"n/m",B6/$B$9)
A13: Stated multiple anchor | B13: 55 | C13: Retro-documented 7/7 = implied P/E@PT (baseline for drift tracking)
A14: Required NTM EPS for PT at stated mult | B14: =IF(ISNUMBER(B13),B5/B13,"—")
A15: Consensus NTM vs required (gap) | B15: =IF(AND(ISNUMBER(B14),ISNUMBER(B9),B9>0),B9/B14-1,"—")
A16: Asymmetry (PT−P)/(P−bear) | B16: =(B5-B4)/(B4-B6)
A18: Methodology (as logged in Decisions Log / note):
A19: June-3 batch rating — no logged multiple anchor (Lesson #2 cohort)
A21: Implied price grid — NTM EPS (rows) × multiple (cols). All formulas.
A22: EPS \ Mult | B22: =IF(ISNUMBER(B12),ROUND(B12,1),ROUND(B10*0.7,1)) | C22: =ROUND(B10,1) | D22: =ROUND(B11,1)
A23: =ROUND($B$9*0.85,2) | B23: =$A23*B$22 | C23: =$A23*C$22 | D23: =$A23*D$22
A24: =ROUND($B$9*1,2) | B24: =$A24*B$22 | C24: =$A24*C$22 | D24: =$A24*D$22
A25: =ROUND($B$9*1.15,2) | B25: =$A25*B$22 | C25: =$A25*C$22 | D25: =$A25*D$22
A27: Audit note:
A28: ⚠️ No bear logged. Was in Hold-PT-Watch band (−1.4%)

Sheet EME
A1: EME — PT Audit Model (EPS × multiple) — Hold
A2: Built 2026-07-07 (evening). Consensus: Robinhood quarterly estimates 7/7 (next two quarters; NTM = 2 × sum — approximation, refine as quarters print). Prices: FMP official closes 7/7. Blue = input, Black = formula.
A4: Current price ($) | B4: 768.38
A5: Our PT ($) | B5: 1000
A6: Bear ($) | B6: 480
A7: Cons EPS — Q+1e | B7: 7.26
A8: Cons EPS — Q+2e | B8: 7.49
A9: NTM EPS (approx = 2×(B7+B8)) | B9: =2*(B7+B8)
A10: P/E at current price | B10: =IF($B$9<=0,"n/m",B4/$B$9)
A11: P/E implied at PT | B11: =IF($B$9<=0,"n/m",B5/$B$9)
A12: P/E implied at bear | B12: =IF($B$9<=0,"n/m",B6/$B$9)
A13: Stated multiple anchor | B13: 30
A14: Required NTM EPS for PT at stated mult | B14: =IF(ISNUMBER(B13),B5/B13,"—")
A15: Consensus NTM vs required (gap) | B15: =IF(AND(ISNUMBER(B14),ISNUMBER(B9),B9>0),B9/B14-1,"—")
A16: Asymmetry (PT−P)/(P−bear) | B16: =(B5-B4)/(B4-B6)
A18: Methodology (as logged in Decisions Log / note):
A19: 30x FY2027E EPS ~$33.50 (6/29 initiation)
A21: Implied price grid — NTM EPS (rows) × multiple (cols). All formulas.
A22: EPS \ Mult | B22: =IF(ISNUMBER(B12),ROUND(B12,1),ROUND(B10*0.7,1)) | C22: =ROUND(B10,1) | D22: =ROUND(B11,1)
A23: =ROUND($B$9*0.85,2) | B23: =$A23*B$22 | C23: =$A23*C$22 | D23: =$A23*D$22
A24: =ROUND($B$9*1,2) | B24: =$A24*B$22 | C24: =$A24*C$22 | D24: =$A24*D$22
A25: =ROUND($B$9*1.15,2) | B25: =$A25*B$22 | C25: =$A25*C$22 | D25: =$A25*D$22
A27: Audit note:
A28: Add zone ≤$660 (asym ≥1.9x); alert live. Q2 upgrade gate: RPO>$16.5B + EPS≥$7.50 + guide≥$31

Sheet EQIX
A1: EQIX — PT Audit Model (EPS × multiple) — Hold
A2: Built 2026-07-07 (evening). Consensus: Robinhood quarterly estimates 7/7 (next two quarters; NTM = 2 × sum — approximation, refine as quarters print). Prices: FMP official closes 7/7. Blue = input, Black = formula.
A4: Current price ($) | B4: 1022.93
A5: Our PT ($) | B5: 1150
A6: Bear ($) | B6: 685 | C6: SCREENING bear set 7/7: 17x trough AFFO × cons NTM $39.4 — refine at print
A7: Cons EPS — Q+1e | B7: 10.14
A8: Cons EPS — Q+2e | B8: 9.54
A9: NTM EPS (approx = 2×(B7+B8)) | B9: =2*(B7+B8)
A10: P/E at current price | B10: =IF($B$9<=0,"n/m",B4/$B$9)
A11: P/E implied at PT | B11: =IF($B$9<=0,"n/m",B5/$B$9)
A12: P/E implied at bear | B12: =IF($B$9<=0,"n/m",B6/$B$9)
A13: Stated multiple anchor | B13: 29 | C13: Retro-documented 7/7 = implied P/E@PT (baseline for drift tracking)
A14: Required NTM EPS for PT at stated mult | B14: =IF(ISNUMBER(B13),B5/B13,"—")
A15: Consensus NTM vs required (gap) | B15: =IF(AND(ISNUMBER(B14),ISNUMBER(B9),B9>0),B9/B14-1,"—")
A16: Asymmetry (PT−P)/(P−bear) | B16: =(B5-B4)/(B4-B6)
A18: Methodology (as logged in Decisions Log / note):
A19: June-3 batch rating — no logged multiple anchor (Lesson #2 cohort)
A21: Implied price grid — NTM EPS (rows) × multiple (cols). All formulas.
A22: EPS \ Mult | B22: =IF(ISNUMBER(B12),ROUND(B12,1),ROUND(B10*0.7,1)) | C22: =ROUND(B10,1) | D22: =ROUND(B11,1)
A23: =ROUND($B$9*0.85,2) | B23: =$A23*B$22 | C23: =$A23*C$22 | D23: =$A23*D$22
A24: =ROUND($B$9*1,2) | B24: =$A24*B$22 | C24: =$A24*C$22 | D24: =$A24*D$22
A25: =ROUND($B$9*1.15,2) | B25: =$A25*B$22 | C25: =$A25*C$22 | D25: =$A25*D$22
A27: Audit note:
A28: REIT (AFFO-adjacent) + ⚠️ no bear logged

Sheet ETN
A1: ETN — PT Audit Model (EPS × multiple) — Hold
A2: Built 2026-07-07 (evening). Consensus: Robinhood quarterly estimates 7/7 (next two quarters; NTM = 2 × sum — approximation, refine as quarters print). Prices: FMP official closes 7/7. Blue = input, Black = formula.
A4: Current price ($) | B4: 395.68
A5: Our PT ($) | B5: 420
A6: Bear ($) | B6: 250 | C6: SCREENING bear set 7/7: 19x industrial trough × cons NTM $13.18 — refine at print
A7: Cons EPS — Q+1e | B7: 3.08
A8: Cons EPS — Q+2e | B8: 3.51
A9: NTM EPS (approx = 2×(B7+B8)) | B9: =2*(B7+B8)
A10: P/E at current price | B10: =IF($B$9<=0,"n/m",B4/$B$9)
A11: P/E implied at PT | B11: =IF($B$9<=0,"n/m",B5/$B$9)
A12: P/E implied at bear | B12: =IF($B$9<=0,"n/m",B6/$B$9)
A13: Stated multiple anchor | B13: 32 | C13: Retro-documented 7/7 = implied P/E@PT (baseline for drift tracking)
A14: Required NTM EPS for PT at stated mult | B14: =IF(ISNUMBER(B13),B5/B13,"—")
A15: Consensus NTM vs required (gap) | B15: =IF(AND(ISNUMBER(B14),ISNUMBER(B9),B9>0),B9/B14-1,"—")
A16: Asymmetry (PT−P)/(P−bear) | B16: =(B5-B4)/(B4-B6)
A18: Methodology (as logged in Decisions Log / note):
A19: June-3 batch rating — no logged multiple anchor (Lesson #2 cohort)
A21: Implied price grid — NTM EPS (rows) × multiple (cols). All formulas.
A22: EPS \ Mult | B22: =IF(ISNUMBER(B12),ROUND(B12,1),ROUND(B10*0.7,1)) | C22: =ROUND(B10,1) | D22: =ROUND(B11,1)
A23: =ROUND($B$9*0.85,2) | B23: =$A23*B$22 | C23: =$A23*C$22 | D23: =$A23*D$22
A24: =ROUND($B$9*1,2) | B24: =$A24*B$22 | C24: =$A24*C$22 | D24: =$A24*D$22
A25: =ROUND($B$9*1.15,2) | B25: =$A25*B$22 | C25: =$A25*C$22 | D25: =$A25*D$22
A27: Audit note:
A28: ⚠️ No bear logged — asymmetry incomputable

Sheet FCEL
A1: FCEL — PT Audit Model (EPS × multiple) — Hold
A2: Built 2026-07-07 (evening). Consensus: Robinhood quarterly estimates 7/7 (next two quarters; NTM = 2 × sum — approximation, refine as quarters print). Prices: FMP official closes 7/7. Blue = input, Black = formula.
A4: Current price ($) | B4: 25.96
A5: Our PT ($) | B5: 26
A6: Bear ($) | B6: 12
A7: Cons EPS — Q+1e | B7: -0.37
A8: Cons EPS — Q+2e | B8: -0.39
A9: NTM EPS (approx = 2×(B7+B8)) | B9: =2*(B7+B8)
A10: P/E at current price | B10: =IF($B$9<=0,"n/m",B4/$B$9)
A11: P/E implied at PT | B11: =IF($B$9<=0,"n/m",B5/$B$9)
A12: P/E implied at bear | B12: =IF($B$9<=0,"n/m",B6/$B$9)
A13: Stated multiple anchor | B13: —
A14: Required NTM EPS for PT at stated mult | B14: —
A15: Consensus NTM vs required (gap) | B15: —
A16: Asymmetry (PT−P)/(P−bear) | B16: =(B5-B4)/(B4-B6)
A18: Methodology (as logged in Decisions Log / note):
A19: Consensus-cluster $26 (7/2 reset); active anti-momentum lean
A21: Grid omitted — EPS-negative / derived-price name; P/E framework not meaningful.
A27: Audit note:
A28: EPS-negative. $200M offering 7/7 AH (~10–11.5% dilution) — watch pricing
A31: REVENUE FRAMEWORK (added 7/7 evening — EPS-negative/near-zero name)
A32: Vault anchors used (consensus revenue unavailable on current data plan); audit = growth embedded in the PT.
A33: Market cap 7/7 ($B) | B33: 1.375
A34: Net debt ($B) | B34: —
A35: Vault revenue anchor (EV/Rev x) | B35: —
A36: Run-rate revenue ($B) | B36: 0.142 | C36: Q2 FY2026 $35.6M × 4 (−5% YoY)
A37: Cap @ PT ($B) | B37: =B33*B5/B4
A38: EV @ PT ($B) | B38: =B37+IF(ISNUMBER(B34),B34,0)
A39: Implied NTM revenue the PT requires ($B) | B39: =IF(ISNUMBER(B35),B38/B35,"—")
A40: Growth embedded: implied rev ÷ run-rate | B40: =IF(AND(ISNUMBER(B39),ISNUMBER(B36)),B39/B36,"—")
A41: P/S at price (run-rate) | B41: =IF(ISNUMBER(B36),B33/B36,"—")
A43: Note:
A44: PT is consensus-cluster ($26), not a rev multiple — P/S shown for context. $200M offering 7/7 AH adds ~10–11.5% shares.

Sheet FCX
A1: FCX — PT Audit Model (EPS × multiple) — Hold
A2: Built 2026-07-07 (evening). Consensus: Robinhood quarterly estimates 7/7 (next two quarters; NTM = 2 × sum — approximation, refine as quarters print). Prices: FMP official closes 7/7. Blue = input, Black = formula.
A4: Current price ($) | B4: 59.27
A5: Our PT ($) | B5: 72
A6: Bear ($) | B6: 35 | C6: SCREENING bear set 7/7: note's own bear copper deck $3.25/lb ≈ 2023 trading zone (~13x NTM) — refine at print
A7: Cons EPS — Q+1e | B7: 0.6
A8: Cons EPS — Q+2e | B8: 0.77
A9: NTM EPS (approx = 2×(B7+B8)) | B9: =2*(B7+B8)
A10: P/E at current price | B10: =IF($B$9<=0,"n/m",B4/$B$9)
A11: P/E implied at PT | B11: =IF($B$9<=0,"n/m",B5/$B$9)
A12: P/E implied at bear | B12: =IF($B$9<=0,"n/m",B6/$B$9)
A13: Stated multiple anchor | B13: —
A14: Required NTM EPS for PT at stated mult | B14: —
A15: Consensus NTM vs required (gap) | B15: —
A16: Asymmetry (PT−P)/(P−bear) | B16: =(B5-B4)/(B4-B6)
A18: Methodology (as logged in Decisions Log / note):
A19: Copper-price scenario deck (bear $3.25/lb basis, not a price)
A21: Implied price grid — NTM EPS (rows) × multiple (cols). All formulas.
A22: EPS \ Mult | B22: =IF(ISNUMBER(B12),ROUND(B12,1),ROUND(B10*0.7,1)) | C22: =ROUND(B10,1) | D22: =ROUND(B11,1)
A23: =ROUND($B$9*0.85,2) | B23: =$A23*B$22 | C23: =$A23*C$22 | D23: =$A23*D$22
A24: =ROUND($B$9*1,2) | B24: =$A24*B$22 | C24: =$A24*C$22 | D24: =$A24*D$22
A25: =ROUND($B$9*1.15,2) | B25: =$A25*B$22 | C25: =$A25*C$22 | D25: =$A25*D$22
A27: Audit note:
A28: ⚠️ No $-bear logged (commodity-deck bear) — asymmetry incomputable

Sheet GLW
A1: GLW — PT Audit Model (EPS × multiple) — Hold
A2: Built 2026-07-07 (evening). Consensus: Robinhood quarterly estimates 7/7 (next two quarters; NTM = 2 × sum — approximation, refine as quarters print). Prices: FMP official closes 7/7. Blue = input, Black = formula.
A4: Current price ($) | B4: 185.38
A5: Our PT ($) | B5: 210
A6: Bear ($) | B6: 95 | C6: SCREENING bear set 7/7: AI-optical premium unwind — 30x × cons NTM $3.20 — refine at print
A7: Cons EPS — Q+1e | B7: 0.75
A8: Cons EPS — Q+2e | B8: 0.85
A9: NTM EPS (approx = 2×(B7+B8)) | B9: =2*(B7+B8)
A10: P/E at current price | B10: =IF($B$9<=0,"n/m",B4/$B$9)
A11: P/E implied at PT | B11: =IF($B$9<=0,"n/m",B5/$B$9)
A12: P/E implied at bear | B12: =IF($B$9<=0,"n/m",B6/$B$9)
A13: Stated multiple anchor | B13: 33 | C13: Retro-documented 7/7 = implied P/E@PT (baseline for drift tracking)
A14: Required NTM EPS for PT at stated mult | B14: =IF(ISNUMBER(B13),B5/B13,"—")
A15: Consensus NTM vs required (gap) | B15: =IF(AND(ISNUMBER(B14),ISNUMBER(B9),B9>0),B9/B14-1,"—")
A16: Asymmetry (PT−P)/(P−bear) | B16: =(B5-B4)/(B4-B6)
A18: Methodology (as logged in Decisions Log / note):
A19: June-3 batch rating — no logged multiple anchor (Lesson #2 cohort)
A21: Implied price grid — NTM EPS (rows) × multiple (cols). All formulas.
A22: EPS \ Mult | B22: =IF(ISNUMBER(B12),ROUND(B12,1),ROUND(B10*0.7,1)) | C22: =ROUND(B10,1) | D22: =ROUND(B11,1)
A23: =ROUND($B$9*0.85,2) | B23: =$A23*B$22 | C23: =$A23*C$22 | D23: =$A23*D$22
A24: =ROUND($B$9*1,2) | B24: =$A24*B$22 | C24: =$A24*C$22 | D24: =$A24*D$22
A25: =ROUND($B$9*1.15,2) | B25: =$A25*B$22 | C25: =$A25*C$22 | D25: =$A25*D$22
A27: Audit note:
A28: ⚠️ No bear logged. Retired from Hold-PT-Watch band 7/7 (−12%)

Sheet HUT
A1: HUT — PT Audit Model (EPS × multiple) — Hold
A2: Built 2026-07-07 (evening). Consensus: Robinhood quarterly estimates 7/7 (next two quarters; NTM = 2 × sum — approximation, refine as quarters print). Prices: FMP official closes 7/7. Blue = input, Black = formula.
A4: Current price ($) | B4: 96.74
A5: Our PT ($) | B5: 145
A6: Bear ($) | B6: 45 | C6: SCREENING bear set 7/7: asset-based placeholder ≈ pre-rerate range [VERIFY at Aug 6 print — needs HODL/MW math] — refine at print
A7: Cons EPS — Q+1e | B7: -0.32
A8: Cons EPS — Q+2e | B8: -0.4
A9: NTM EPS (approx = 2×(B7+B8)) | B9: =2*(B7+B8)
A10: P/E at current price | B10: =IF($B$9<=0,"n/m",B4/$B$9)
A11: P/E implied at PT | B11: =IF($B$9<=0,"n/m",B5/$B$9)
A12: P/E implied at bear | B12: =IF($B$9<=0,"n/m",B6/$B$9)
A13: Stated multiple anchor | B13: —
A14: Required NTM EPS for PT at stated mult | B14: —
A15: Consensus NTM vs required (gap) | B15: —
A16: Asymmetry (PT−P)/(P−bear) | B16: =(B5-B4)/(B4-B6)
A18: Methodology (as logged in Decisions Log / note):
A19: Comps (miner-to-host); June-3 initiation
A21: Grid omitted — EPS-negative / derived-price name; P/E framework not meaningful.
A27: Audit note:
A28: EPS-negative + ⚠️ no bear logged
A31: REVENUE FRAMEWORK (added 7/7 evening — EPS-negative/near-zero name)
A32: Vault anchors used (consensus revenue unavailable on current data plan); audit = growth embedded in the PT.
A33: Market cap 7/7 ($B) | B33: 10.892
A34: Net debt ($B) | B34: —
A35: Vault revenue anchor (EV/Rev x) | B35: —
A36: Run-rate revenue ($B) | B36: — | C36: —
A37: Cap @ PT ($B) | B37: =B33*B5/B4
A38: EV @ PT ($B) | B38: =B37+IF(ISNUMBER(B34),B34,0)
A39: Implied NTM revenue the PT requires ($B) | B39: =IF(ISNUMBER(B35),B38/B35,"—")
A40: Growth embedded: implied rev ÷ run-rate | B40: =IF(AND(ISNUMBER(B39),ISNUMBER(B36)),B39/B36,"—")
A41: P/S at price (run-rate) | B41: =IF(ISNUMBER(B36),B33/B36,"—")
A43: Note:
A44: No revenue anchor (comps, miner-to-host). Asset-based bear work owed at Aug 6 print.

Sheet INTC
A1: INTC — PT Audit Model (EPS × multiple) — Hold
A2: Built 2026-07-07 (evening). Consensus: Robinhood quarterly estimates 7/7 (next two quarters; NTM = 2 × sum — approximation, refine as quarters print). Prices: FMP official closes 7/7. Blue = input, Black = formula.
A4: Current price ($) | B4: 110.39
A5: Our PT ($) | B5: 120
A6: Bear ($) | B6: 60
A7: Cons EPS — Q+1e | B7: 0.19
A8: Cons EPS — Q+2e | B8: 0.24
A9: NTM EPS (approx = 2×(B7+B8)) | B9: =2*(B7+B8)
A10: P/E at current price | B10: =IF($B$9<=0,"n/m",B4/$B$9)
A11: P/E implied at PT | B11: =IF($B$9<=0,"n/m",B5/$B$9)
A12: P/E implied at bear | B12: =IF($B$9<=0,"n/m",B6/$B$9)
A13: Stated multiple anchor | B13: —
A14: Required NTM EPS for PT at stated mult | B14: —
A15: Consensus NTM vs required (gap) | B15: —
A16: Asymmetry (PT−P)/(P−bear) | B16: =(B5-B4)/(B4-B6)
A18: Methodology (as logged in Decisions Log / note):
A19: Probability-weighted EV ~$106 (decision closed ✗ 6/23; PT never reset)
A21: Implied price grid — NTM EPS (rows) × multiple (cols). All formulas.
A22: EPS \ Mult | B22: =IF(ISNUMBER(B12),ROUND(B12,1),ROUND(B10*0.7,1)) | C22: =ROUND(B10,1) | D22: =ROUND(B11,1)
A23: =ROUND($B$9*0.85,2) | B23: =$A23*B$22 | C23: =$A23*C$22 | D23: =$A23*D$22
A24: =ROUND($B$9*1,2) | B24: =$A24*B$22 | C24: =$A24*C$22 | D24: =$A24*D$22
A25: =ROUND($B$9*1.15,2) | B25: =$A25*B$22 | C25: =$A25*C$22 | D25: =$A25*D$22
A27: Audit note:
A28: Owed post-✗ PT reset — due at Jul 23 print (per Hold PT Watch)

Sheet IREN
A1: IREN — PT Audit Model (EPS × multiple) — Hold
A2: Built 2026-07-07 (evening). Consensus: Robinhood quarterly estimates 7/7 (next two quarters; NTM = 2 × sum — approximation, refine as quarters print). Prices: FMP official closes 7/7. Blue = input, Black = formula.
A4: Current price ($) | B4: 39.82
A5: Our PT ($) | B5: 72
A6: Bear ($) | B6: 18 | C6: SCREENING bear set 7/7: pre-AI-contract trading range; DC-capex funding risk [VERIFY at Aug 27 print] — refine at print
A7: Cons EPS — Q+1e | B7: -0.38
A8: Cons EPS — Q+2e | B8: -0.25
A9: NTM EPS (approx = 2×(B7+B8)) | B9: =2*(B7+B8)
A10: P/E at current price | B10: =IF($B$9<=0,"n/m",B4/$B$9)
A11: P/E implied at PT | B11: =IF($B$9<=0,"n/m",B5/$B$9)
A12: P/E implied at bear | B12: =IF($B$9<=0,"n/m",B6/$B$9)
A13: Stated multiple anchor | B13: —
A14: Required NTM EPS for PT at stated mult | B14: —
A15: Consensus NTM vs required (gap) | B15: —
A16: Asymmetry (PT−P)/(P−bear) | B16: =(B5-B4)/(B4-B6)
A18: Methodology (as logged in Decisions Log / note):
A19: June-3 batch rating — no logged multiple anchor (Lesson #2 cohort)
A21: Grid omitted — EPS-negative / derived-price name; P/E framework not meaningful.
A27: Audit note:
A28: EPS-negative + ⚠️ no bear logged. PT 81% above price — stale?
A31: REVENUE FRAMEWORK (added 7/7 evening — EPS-negative/near-zero name)
A32: Vault anchors used (consensus revenue unavailable on current data plan); audit = growth embedded in the PT.
A33: Market cap 7/7 ($B) | B33: 14.208
A34: Net debt ($B) | B34: —
A35: Vault revenue anchor (EV/Rev x) | B35: —
A36: Run-rate revenue ($B) | B36: — | C36: —
A37: Cap @ PT ($B) | B37: =B33*B5/B4
A38: EV @ PT ($B) | B38: =B37+IF(ISNUMBER(B34),B34,0)
A39: Implied NTM revenue the PT requires ($B) | B39: =IF(ISNUMBER(B35),B38/B35,"—")
A40: Growth embedded: implied rev ÷ run-rate | B40: =IF(AND(ISNUMBER(B39),ISNUMBER(B36)),B39/B36,"—")
A41: P/S at price (run-rate) | B41: =IF(ISNUMBER(B36),B33/B36,"—")
A43: Note:
A44: No revenue anchor. Asset-based bear work owed at Aug 27 print.

Sheet KLAC
A1: KLAC — PT Audit Model (EPS × multiple) — Hold
A2: Built 2026-07-07 (evening). Consensus: Robinhood quarterly estimates 7/7 (next two quarters; NTM = 2 × sum — approximation, refine as quarters print). Prices: FMP official closes 7/7. Blue = input, Black = formula.
A4: Current price ($) | B4: 216.47
A5: Our PT ($) | B5: 270
A6: Bear ($) | B6: 140
A7: Cons EPS — Q+1e | B7: 1
A8: Cons EPS — Q+2e | B8: 1.13
A9: NTM EPS (approx = 2×(B7+B8)) | B9: =2*(B7+B8)
A10: P/E at current price | B10: =IF($B$9<=0,"n/m",B4/$B$9)
A11: P/E implied at PT | B11: =IF($B$9<=0,"n/m",B5/$B$9)
A12: P/E implied at bear | B12: =IF($B$9<=0,"n/m",B6/$B$9)
A13: Stated multiple anchor | B13: 74
A14: Required NTM EPS for PT at stated mult | B14: =IF(ISNUMBER(B13),B5/B13,"—")
A15: Consensus NTM vs required (gap) | B15: =IF(AND(ISNUMBER(B14),ISNUMBER(B9),B9>0),B9/B14-1,"—")
A16: Asymmetry (PT−P)/(P−bear) | B16: =(B5-B4)/(B4-B6)
A18: Methodology (as logged in Decisions Log / note):
A19: 74x FY2026E post-split EPS ~$3.66 (6/29 reset); revisit closed 7/7
A21: Implied price grid — NTM EPS (rows) × multiple (cols). All formulas.
A22: EPS \ Mult | B22: =IF(ISNUMBER(B12),ROUND(B12,1),ROUND(B10*0.7,1)) | C22: =ROUND(B10,1) | D22: =ROUND(B11,1)
A23: =ROUND($B$9*0.85,2) | B23: =$A23*B$22 | C23: =$A23*C$22 | D23: =$A23*D$22
A24: =ROUND($B$9*1,2) | B24: =$A24*B$22 | C24: =$A24*C$22 | D24: =$A24*D$22
A25: =ROUND($B$9*1.15,2) | B25: =$A25*B$22 | C25: =$A25*C$22 | D25: =$A25*D$22
A27: Audit note:
A28: Post-split estimates ($1.00/$1.13). Asym ~0.7x at close

Sheet MKSI
A1: MKSI — PT Audit Model (EPS × multiple) — Hold
A2: Built 2026-07-07 (evening). Consensus: Robinhood quarterly estimates 7/7 (next two quarters; NTM = 2 × sum — approximation, refine as quarters print). Prices: FMP official closes 7/7. Blue = input, Black = formula.
A4: Current price ($) | B4: 349.57
A5: Our PT ($) | B5: 450
A6: Bear ($) | B6: 230
A7: Cons EPS — Q+1e | B7: 2.95
A8: Cons EPS — Q+2e | B8: 3.17
A9: NTM EPS (approx = 2×(B7+B8)) | B9: =2*(B7+B8)
A10: P/E at current price | B10: =IF($B$9<=0,"n/m",B4/$B$9)
A11: P/E implied at PT | B11: =IF($B$9<=0,"n/m",B5/$B$9)
A12: P/E implied at bear | B12: =IF($B$9<=0,"n/m",B6/$B$9)
A13: Stated multiple anchor | B13: 35
A14: Required NTM EPS for PT at stated mult | B14: =IF(ISNUMBER(B13),B5/B13,"—")
A15: Consensus NTM vs required (gap) | B15: =IF(AND(ISNUMBER(B14),ISNUMBER(B9),B9>0),B9/B14-1,"—")
A16: Asymmetry (PT−P)/(P−bear) | B16: =(B5-B4)/(B4-B6)
A18: Methodology (as logged in Decisions Log / note):
A19: 35x NTM ~$12.75 (7/2 reset); deep-dive cleared 7/7 (leverage 3.5x)
A21: Implied price grid — NTM EPS (rows) × multiple (cols). All formulas.
A22: EPS \ Mult | B22: =IF(ISNUMBER(B12),ROUND(B12,1),ROUND(B10*0.7,1)) | C22: =ROUND(B10,1) | D22: =ROUND(B11,1)
A23: =ROUND($B$9*0.85,2) | B23: =$A23*B$22 | C23: =$A23*C$22 | D23: =$A23*D$22
A24: =ROUND($B$9*1,2) | B24: =$A24*B$22 | C24: =$A24*C$22 | D24: =$A24*D$22
A25: =ROUND($B$9*1.15,2) | B25: =$A25*B$22 | C25: =$A25*C$22 | D25: =$A25*D$22
A27: Audit note:
A28: Upgrade gate: leverage <2.5x AND asym ≥1.5x (≤$318)

Sheet MPWR
A1: MPWR — PT Audit Model (EPS × multiple) — Hold
A2: Built 2026-07-07 (evening). Consensus: Robinhood quarterly estimates 7/7 (next two quarters; NTM = 2 × sum — approximation, refine as quarters print). Prices: FMP official closes 7/7. Blue = input, Black = formula.
A4: Current price ($) | B4: 1272.81
A5: Our PT ($) | B5: 1700
A6: Bear ($) | B6: 735 | C6: SCREENING bear set 7/7: 31x analog trough × cons NTM $23.72 — refine at print
A7: Cons EPS — Q+1e | B7: 5.65
A8: Cons EPS — Q+2e | B8: 6.21
A9: NTM EPS (approx = 2×(B7+B8)) | B9: =2*(B7+B8)
A10: P/E at current price | B10: =IF($B$9<=0,"n/m",B4/$B$9)
A11: P/E implied at PT | B11: =IF($B$9<=0,"n/m",B5/$B$9)
A12: P/E implied at bear | B12: =IF($B$9<=0,"n/m",B6/$B$9)
A13: Stated multiple anchor | B13: 72 | C13: Retro-documented 7/7 = implied P/E@PT (baseline for drift tracking)
A14: Required NTM EPS for PT at stated mult | B14: =IF(ISNUMBER(B13),B5/B13,"—")
A15: Consensus NTM vs required (gap) | B15: =IF(AND(ISNUMBER(B14),ISNUMBER(B9),B9>0),B9/B14-1,"—")
A16: Asymmetry (PT−P)/(P−bear) | B16: =(B5-B4)/(B4-B6)
A18: Methodology (as logged in Decisions Log / note):
A19: June-3 batch rating — no logged multiple anchor (Lesson #2 cohort)
A21: Implied price grid — NTM EPS (rows) × multiple (cols). All formulas.
A22: EPS \ Mult | B22: =IF(ISNUMBER(B12),ROUND(B12,1),ROUND(B10*0.7,1)) | C22: =ROUND(B10,1) | D22: =ROUND(B11,1)
A23: =ROUND($B$9*0.85,2) | B23: =$A23*B$22 | C23: =$A23*C$22 | D23: =$A23*D$22
A24: =ROUND($B$9*1,2) | B24: =$A24*B$22 | C24: =$A24*C$22 | D24: =$A24*D$22
A25: =ROUND($B$9*1.15,2) | B25: =$A25*B$22 | C25: =$A25*C$22 | D25: =$A25*D$22
A27: Audit note:
A28: ⚠️ No bear logged. PT 34% above price — stale?

Sheet NVT
A1: NVT — PT Audit Model (EPS × multiple) — Hold
A2: Built 2026-07-07 (evening). Consensus: Robinhood quarterly estimates 7/7 (next two quarters; NTM = 2 × sum — approximation, refine as quarters print). Prices: FMP official closes 7/7. Blue = input, Black = formula.
A4: Current price ($) | B4: 153.18
A5: Our PT ($) | B5: 180
A6: Bear ($) | B6: 85 | C6: SCREENING bear set 7/7: note's own logic — re-rate to industrial multiple (~18x × cons NTM $4.68) — refine at print
A7: Cons EPS — Q+1e | B7: 1.16
A8: Cons EPS — Q+2e | B8: 1.18
A9: NTM EPS (approx = 2×(B7+B8)) | B9: =2*(B7+B8)
A10: P/E at current price | B10: =IF($B$9<=0,"n/m",B4/$B$9)
A11: P/E implied at PT | B11: =IF($B$9<=0,"n/m",B5/$B$9)
A12: P/E implied at bear | B12: =IF($B$9<=0,"n/m",B6/$B$9)
A13: Stated multiple anchor | B13: 38 | C13: Retro-documented 7/7 = implied P/E@PT (baseline for drift tracking)
A14: Required NTM EPS for PT at stated mult | B14: =IF(ISNUMBER(B13),B5/B13,"—")
A15: Consensus NTM vs required (gap) | B15: =IF(AND(ISNUMBER(B14),ISNUMBER(B9),B9>0),B9/B14-1,"—")
A16: Asymmetry (PT−P)/(P−bear) | B16: =(B5-B4)/(B4-B6)
A18: Methodology (as logged in Decisions Log / note):
A19: June-3 batch rating — no logged multiple anchor (Lesson #2 cohort)
A21: Implied price grid — NTM EPS (rows) × multiple (cols). All formulas.
A22: EPS \ Mult | B22: =IF(ISNUMBER(B12),ROUND(B12,1),ROUND(B10*0.7,1)) | C22: =ROUND(B10,1) | D22: =ROUND(B11,1)
A23: =ROUND($B$9*0.85,2) | B23: =$A23*B$22 | C23: =$A23*C$22 | D23: =$A23*D$22
A24: =ROUND($B$9*1,2) | B24: =$A24*B$22 | C24: =$A24*C$22 | D24: =$A24*D$22
A25: =ROUND($B$9*1.15,2) | B25: =$A25*B$22 | C25: =$A25*C$22 | D25: =$A25*D$22
A27: Audit note:
A28: ⚠️ No bear logged — asymmetry incomputable

Sheet ON
A1: ON — PT Audit Model (EPS × multiple) — Hold
A2: Built 2026-07-07 (evening). Consensus: Robinhood quarterly estimates 7/7 (next two quarters; NTM = 2 × sum — approximation, refine as quarters print). Prices: FMP official closes 7/7. Blue = input, Black = formula.
A4: Current price ($) | B4: 91.1
A5: Our PT ($) | B5: 100
A6: Bear ($) | B6: 65
A7: Cons EPS — Q+1e | B7: 0.71
A8: Cons EPS — Q+2e | B8: 0.83
A9: NTM EPS (approx = 2×(B7+B8)) | B9: =2*(B7+B8)
A10: P/E at current price | B10: =IF($B$9<=0,"n/m",B4/$B$9)
A11: P/E implied at PT | B11: =IF($B$9<=0,"n/m",B5/$B$9)
A12: P/E implied at bear | B12: =IF($B$9<=0,"n/m",B6/$B$9)
A13: Stated multiple anchor | B13: —
A14: Required NTM EPS for PT at stated mult | B14: —
A15: Consensus NTM vs required (gap) | B15: —
A16: Asymmetry (PT−P)/(P−bear) | B16: =(B5-B4)/(B4-B6)
A18: Methodology (as logged in Decisions Log / note):
A19: Comps post-Synaptics downgrade (6/29); bear $65 integration-failure
A21: Implied price grid — NTM EPS (rows) × multiple (cols). All formulas.
A22: EPS \ Mult | B22: =IF(ISNUMBER(B12),ROUND(B12,1),ROUND(B10*0.7,1)) | C22: =ROUND(B10,1) | D22: =ROUND(B11,1)
A23: =ROUND($B$9*0.85,2) | B23: =$A23*B$22 | C23: =$A23*C$22 | D23: =$A23*D$22
A24: =ROUND($B$9*1,2) | B24: =$A24*B$22 | C24: =$A24*C$22 | D24: =$A24*D$22
A25: =ROUND($B$9*1.15,2) | B25: =$A25*B$22 | C25: =$A25*C$22 | D25: =$A25*D$22
A27: Audit note:
A28: Re-entry: synergy proof or $70–75 pullback

Sheet PWR
A1: PWR — PT Audit Model (EPS × multiple) — Hold
A2: Built 2026-07-07 (evening). Consensus: Robinhood quarterly estimates 7/7 (next two quarters; NTM = 2 × sum — approximation, refine as quarters print). Prices: FMP official closes 7/7. Blue = input, Black = formula.
A4: Current price ($) | B4: 656.79
A5: Our PT ($) | B5: 680
A6: Bear ($) | B6: 370 | C6: SCREENING bear set 7/7: 25x premium-E&C trough × cons NTM $14.82 — refine at print
A7: Cons EPS — Q+1e | B7: 3.25
A8: Cons EPS — Q+2e | B8: 4.16
A9: NTM EPS (approx = 2×(B7+B8)) | B9: =2*(B7+B8)
A10: P/E at current price | B10: =IF($B$9<=0,"n/m",B4/$B$9)
A11: P/E implied at PT | B11: =IF($B$9<=0,"n/m",B5/$B$9)
A12: P/E implied at bear | B12: =IF($B$9<=0,"n/m",B6/$B$9)
A13: Stated multiple anchor | B13: 23 | C13: Retro-documented 7/7 = implied P/E@PT (baseline for drift tracking)
A14: Required NTM EPS for PT at stated mult | B14: =IF(ISNUMBER(B13),B5/B13,"—")
A15: Consensus NTM vs required (gap) | B15: =IF(AND(ISNUMBER(B14),ISNUMBER(B9),B9>0),B9/B14-1,"—")
A16: Asymmetry (PT−P)/(P−bear) | B16: =(B5-B4)/(B4-B6)
A18: Methodology (as logged in Decisions Log / note):
A19: June-3 batch rating — no logged multiple anchor (Lesson #2 cohort)
A21: Implied price grid — NTM EPS (rows) × multiple (cols). All formulas.
A22: EPS \ Mult | B22: =IF(ISNUMBER(B12),ROUND(B12,1),ROUND(B10*0.7,1)) | C22: =ROUND(B10,1) | D22: =ROUND(B11,1)
A23: =ROUND($B$9*0.85,2) | B23: =$A23*B$22 | C23: =$A23*C$22 | D23: =$A23*D$22
A24: =ROUND($B$9*1,2) | B24: =$A24*B$22 | C24: =$A24*C$22 | D24: =$A24*D$22
A25: =ROUND($B$9*1.15,2) | B25: =$A25*B$22 | C25: =$A25*C$22 | D25: =$A25*D$22
A27: Audit note:
A28: ⚠️ No bear logged. Hold-PT-Watch band edge (−3.4%)

Sheet SCCO
A1: SCCO — PT Audit Model (EPS × multiple) — Hold
A2: Built 2026-07-07 (evening). Consensus: Robinhood quarterly estimates 7/7 (next two quarters; NTM = 2 × sum — approximation, refine as quarters print). Prices: FMP official closes 7/7. Blue = input, Black = formula.
A4: Current price ($) | B4: 169.75
A5: Our PT ($) | B5: 165
A6: Bear ($) | B6: 105 | C6: SCREENING bear set 7/7: bear copper deck — ~15x × cons NTM $7.12 — refine at print
A7: Cons EPS — Q+1e | B7: 1.81
A8: Cons EPS — Q+2e | B8: 1.75
A9: NTM EPS (approx = 2×(B7+B8)) | B9: =2*(B7+B8)
A10: P/E at current price | B10: =IF($B$9<=0,"n/m",B4/$B$9)
A11: P/E implied at PT | B11: =IF($B$9<=0,"n/m",B5/$B$9)
A12: P/E implied at bear | B12: =IF($B$9<=0,"n/m",B6/$B$9)
A13: Stated multiple anchor | B13: 23 | C13: Retro-documented 7/7 = implied P/E@PT (baseline for drift tracking)
A14: Required NTM EPS for PT at stated mult | B14: =IF(ISNUMBER(B13),B5/B13,"—")
A15: Consensus NTM vs required (gap) | B15: =IF(AND(ISNUMBER(B14),ISNUMBER(B9),B9>0),B9/B14-1,"—")
A16: Asymmetry (PT−P)/(P−bear) | B16: =(B5-B4)/(B4-B6)
A18: Methodology (as logged in Decisions Log / note):
A19: June-3 batch rating; low-conviction note
A21: Implied price grid — NTM EPS (rows) × multiple (cols). All formulas.
A22: EPS \ Mult | B22: =IF(ISNUMBER(B12),ROUND(B12,1),ROUND(B10*0.7,1)) | C22: =ROUND(B10,1) | D22: =ROUND(B11,1)
A23: =ROUND($B$9*0.85,2) | B23: =$A23*B$22 | C23: =$A23*C$22 | D23: =$A23*D$22
A24: =ROUND($B$9*1,2) | B24: =$A24*B$22 | C24: =$A24*C$22 | D24: =$A24*D$22
A25: =ROUND($B$9*1.15,2) | B25: =$A25*B$22 | C25: =$A25*C$22 | D25: =$A25*D$22
A27: Audit note:
A28: ⚠️ ABOVE PT (+2.9%) + no bear — Rule-2 decision owed at Jul 28 print

Sheet SNDK
A1: SNDK — PT Audit Model (EPS × multiple) — Hold
A2: Built 2026-07-07 (evening). Consensus: Robinhood quarterly estimates 7/7 (next two quarters; NTM = 2 × sum — approximation, refine as quarters print). Prices: FMP official closes 7/7. Blue = input, Black = formula.
A4: Current price ($) | B4: 1617.7
A5: Our PT ($) | B5: 2000
A6: Bear ($) | B6: 400
A7: Cons EPS — Q+1e | B7: 33.38
A8: Cons EPS — Q+2e | B8: 41.45
A9: NTM EPS (approx = 2×(B7+B8)) | B9: =2*(B7+B8)
A10: P/E at current price | B10: =IF($B$9<=0,"n/m",B4/$B$9)
A11: P/E implied at PT | B11: =IF($B$9<=0,"n/m",B5/$B$9)
A12: P/E implied at bear | B12: =IF($B$9<=0,"n/m",B6/$B$9)
A13: Stated multiple anchor | B13: —
A14: Required NTM EPS for PT at stated mult | B14: —
A15: Consensus NTM vs required (gap) | B15: —
A16: Asymmetry (PT−P)/(P−bear) | B16: =(B5-B4)/(B4-B6)
A18: Methodology (as logged in Decisions Log / note):
A19: PT STALE — gated to Aug 13 three-condition upgrade gate (EPS≥$38 + 6th NBM + Q1 guide≥$35)
A21: Implied price grid — NTM EPS (rows) × multiple (cols). All formulas.
A22: EPS \ Mult | B22: =IF(ISNUMBER(B12),ROUND(B12,1),ROUND(B10*0.7,1)) | C22: =ROUND(B10,1) | D22: =ROUND(B11,1)
A23: =ROUND($B$9*0.85,2) | B23: =$A23*B$22 | C23: =$A23*C$22 | D23: =$A23*D$22
A24: =ROUND($B$9*1,2) | B24: =$A24*B$22 | C24: =$A24*C$22 | D24: =$A24*D$22
A25: =ROUND($B$9*1.15,2) | B25: =$A25*B$22 | C25: =$A25*C$22 | D25: =$A25*D$22
A27: Audit note:
A28: Now 19% BELOW stale PT — asymmetry flipped favorable into gate

Sheet STX
A1: STX — PT Audit Model (EPS × multiple) — Hold
A2: Built 2026-07-07 (evening). Consensus: Robinhood quarterly estimates 7/7 (next two quarters; NTM = 2 × sum — approximation, refine as quarters print). Prices: FMP official closes 7/7. Blue = input, Black = formula.
A4: Current price ($) | B4: 827.64
A5: Our PT ($) | B5: 910
A6: Bear ($) | B6: 240 | C6: SCREENING bear set 7/7: memory-cycle bear — EPS halves to ~$12, 20x trough (SNDK-consistent treatment) — refine at print
A7: Cons EPS — Q+1e | B7: 5.04
A8: Cons EPS — Q+2e | B8: 5.63
A9: NTM EPS (approx = 2×(B7+B8)) | B9: =2*(B7+B8)
A10: P/E at current price | B10: =IF($B$9<=0,"n/m",B4/$B$9)
A11: P/E implied at PT | B11: =IF($B$9<=0,"n/m",B5/$B$9)
A12: P/E implied at bear | B12: =IF($B$9<=0,"n/m",B6/$B$9)
A13: Stated multiple anchor | B13: 43 | C13: Retro-documented 7/7 = implied P/E@PT (baseline for drift tracking)
A14: Required NTM EPS for PT at stated mult | B14: =IF(ISNUMBER(B13),B5/B13,"—")
A15: Consensus NTM vs required (gap) | B15: =IF(AND(ISNUMBER(B14),ISNUMBER(B9),B9>0),B9/B14-1,"—")
A16: Asymmetry (PT−P)/(P−bear) | B16: =(B5-B4)/(B4-B6)
A18: Methodology (as logged in Decisions Log / note):
A19: June-3 batch rating; thin note (memory-tape caveat)
A21: Implied price grid — NTM EPS (rows) × multiple (cols). All formulas.
A22: EPS \ Mult | B22: =IF(ISNUMBER(B12),ROUND(B12,1),ROUND(B10*0.7,1)) | C22: =ROUND(B10,1) | D22: =ROUND(B11,1)
A23: =ROUND($B$9*0.85,2) | B23: =$A23*B$22 | C23: =$A23*C$22 | D23: =$A23*D$22
A24: =ROUND($B$9*1,2) | B24: =$A24*B$22 | C24: =$A24*C$22 | D24: =$A24*D$22
A25: =ROUND($B$9*1.15,2) | B25: =$A25*B$22 | C25: =$A25*C$22 | D25: =$A25*D$22
A27: Audit note:
A28: ⚠️ No bear logged. Deepen note before Jul 28 print

Sheet TOELY
A1: TOELY — PT Audit Model (EPS × multiple) — Hold
A2: Built 2026-07-07 (evening). Consensus: Robinhood quarterly estimates 7/7 (next two quarters; NTM = 2 × sum — approximation, refine as quarters print). Prices: FMP official closes 7/7. Blue = input, Black = formula.
A4: Current price ($) | B4: 209.8
A5: Our PT ($) | B5: 220
A6: Bear ($) | B6: 110
A7: Cons EPS — Q+1e | B7: 1.205 | C7: Vault FX-honest base ADR EPS $4.82/yr ÷ 4 per quarter (7/7 downgrade) — NOT consensus. Check: 45x × $4.82 = $217 ≈ PT $220 ✓
A8: Cons EPS — Q+2e | B8: 1.205
A9: NTM EPS (approx = 2×(B7+B8)) | B9: =2*(B7+B8)
A10: P/E at current price | B10: =IF($B$9<=0,"n/m",B4/$B$9)
A11: P/E implied at PT | B11: =IF($B$9<=0,"n/m",B5/$B$9)
A12: P/E implied at bear | B12: =IF($B$9<=0,"n/m",B6/$B$9)
A13: Stated multiple anchor | B13: 45
A14: Required NTM EPS for PT at stated mult | B14: =IF(ISNUMBER(B13),B5/B13,"—")
A15: Consensus NTM vs required (gap) | B15: =IF(AND(ISNUMBER(B14),ISNUMBER(B9),B9>0),B9/B14-1,"—")
A16: Asymmetry (PT−P)/(P−bear) | B16: =(B5-B4)/(B4-B6)
A18: Methodology (as logged in Decisions Log / note):
A19: 45x FX-honest bull ADR EPS $4.82 (7/7 downgrade; ¥161.9 basis)
A21: Implied price grid — NTM EPS (rows) × multiple (cols). All formulas.
A22: EPS \ Mult | B22: =IF(ISNUMBER(B12),ROUND(B12,1),ROUND(B10*0.7,1)) | C22: =ROUND(B10,1) | D22: =ROUND(B11,1)
A23: =ROUND($B$9*0.85,2) | B23: =$A23*B$22 | C23: =$A23*C$22 | D23: =$A23*D$22
A24: =ROUND($B$9*1,2) | B24: =$A24*B$22 | C24: =$A24*C$22 | D24: =$A24*D$22
A25: =ROUND($B$9*1.15,2) | B25: =$A25*B$22 | C25: =$A25*C$22 | D25: =$A25*D$22
A27: Audit note:
A28: No US consensus — vault EPS input. Upgrade: FY27H1 ¥-EPS ≥¥1,900 or ≤$150

Sheet TSEM
A1: TSEM — PT Audit Model (EPS × multiple) — Hold
A2: Built 2026-07-07 (evening). Consensus: Robinhood quarterly estimates 7/7 (next two quarters; NTM = 2 × sum — approximation, refine as quarters print). Prices: FMP official closes 7/7. Blue = input, Black = formula.
A4: Current price ($) | B4: 211.93
A5: Our PT ($) | B5: 285
A6: Bear ($) | B6: 95 | C6: SCREENING bear set 7/7: 30x × cons NTM $3.18 — reversion toward pre-AI-rerate zone — refine at print
A7: Cons EPS — Q+1e | B7: 0.73
A8: Cons EPS — Q+2e | B8: 0.86
A9: NTM EPS (approx = 2×(B7+B8)) | B9: =2*(B7+B8)
A10: P/E at current price | B10: =IF($B$9<=0,"n/m",B4/$B$9)
A11: P/E implied at PT | B11: =IF($B$9<=0,"n/m",B5/$B$9)
A12: P/E implied at bear | B12: =IF($B$9<=0,"n/m",B6/$B$9)
A13: Stated multiple anchor | B13: 45 | C13: Retro-documented 7/7 = implied P/E@PT (baseline for drift tracking)
A14: Required NTM EPS for PT at stated mult | B14: =IF(ISNUMBER(B13),B5/B13,"—")
A15: Consensus NTM vs required (gap) | B15: =IF(AND(ISNUMBER(B14),ISNUMBER(B9),B9>0),B9/B14-1,"—")
A16: Asymmetry (PT−P)/(P−bear) | B16: =(B5-B4)/(B4-B6)
A18: Methodology (as logged in Decisions Log / note):
A19: Comps (June-3); 'next Hold to test' per Lesson #3 — now −26% below PT
A21: Implied price grid — NTM EPS (rows) × multiple (cols). All formulas.
A22: EPS \ Mult | B22: =IF(ISNUMBER(B12),ROUND(B12,1),ROUND(B10*0.7,1)) | C22: =ROUND(B10,1) | D22: =ROUND(B11,1)
A23: =ROUND($B$9*0.85,2) | B23: =$A23*B$22 | C23: =$A23*C$22 | D23: =$A23*D$22
A24: =ROUND($B$9*1,2) | B24: =$A24*B$22 | C24: =$A24*C$22 | D24: =$A24*D$22
A25: =ROUND($B$9*1.15,2) | B25: =$A25*B$22 | C25: =$A25*C$22 | D25: =$A25*D$22
A27: Audit note:
A28: ⚠️ No bear logged — asymmetry incomputable

Sheet TT
A1: TT — PT Audit Model (EPS × multiple) — Hold
A2: Built 2026-07-07 (evening). Consensus: Robinhood quarterly estimates 7/7 (next two quarters; NTM = 2 × sum — approximation, refine as quarters print). Prices: FMP official closes 7/7. Blue = input, Black = formula.
A4: Current price ($) | B4: 475.74
A5: Our PT ($) | B5: 515
A6: Bear ($) | B6: 300 | C6: SCREENING bear set 7/7: 17x industrial trough × cons NTM $17.66 — refine at print
A7: Cons EPS — Q+1e | B7: 4.25
A8: Cons EPS — Q+2e | B8: 4.58
A9: NTM EPS (approx = 2×(B7+B8)) | B9: =2*(B7+B8)
A10: P/E at current price | B10: =IF($B$9<=0,"n/m",B4/$B$9)
A11: P/E implied at PT | B11: =IF($B$9<=0,"n/m",B5/$B$9)
A12: P/E implied at bear | B12: =IF($B$9<=0,"n/m",B6/$B$9)
A13: Stated multiple anchor | B13: 29 | C13: Retro-documented 7/7 = implied P/E@PT (baseline for drift tracking)
A14: Required NTM EPS for PT at stated mult | B14: =IF(ISNUMBER(B13),B5/B13,"—")
A15: Consensus NTM vs required (gap) | B15: =IF(AND(ISNUMBER(B14),ISNUMBER(B9),B9>0),B9/B14-1,"—")
A16: Asymmetry (PT−P)/(P−bear) | B16: =(B5-B4)/(B4-B6)
A18: Methodology (as logged in Decisions Log / note):
A19: June-3 batch rating — no logged multiple anchor (Lesson #2 cohort)
A21: Implied price grid — NTM EPS (rows) × multiple (cols). All formulas.
A22: EPS \ Mult | B22: =IF(ISNUMBER(B12),ROUND(B12,1),ROUND(B10*0.7,1)) | C22: =ROUND(B10,1) | D22: =ROUND(B11,1)
A23: =ROUND($B$9*0.85,2) | B23: =$A23*B$22 | C23: =$A23*C$22 | D23: =$A23*D$22
A24: =ROUND($B$9*1,2) | B24: =$A24*B$22 | C24: =$A24*C$22 | D24: =$A24*D$22
A25: =ROUND($B$9*1.15,2) | B25: =$A25*B$22 | C25: =$A25*C$22 | D25: =$A25*D$22
A27: Audit note:
A28: ⚠️ No bear logged — asymmetry incomputable

Sheet WDC
A1: WDC — PT Audit Model (EPS × multiple) — Hold
A2: Built 2026-07-07 (evening). Consensus: Robinhood quarterly estimates 7/7 (next two quarters; NTM = 2 × sum — approximation, refine as quarters print). Prices: FMP official closes 7/7. Blue = input, Black = formula.
A4: Current price ($) | B4: 532.1
A5: Our PT ($) | B5: 560
A6: Bear ($) | B6: 160 | C6: SCREENING bear set 7/7: memory-cycle bear — EPS halves to ~$8, 20x trough (STX/SNDK-consistent) — refine at print
A7: Cons EPS — Q+1e | B7: 3.27
A8: Cons EPS — Q+2e | B8: 3.63
A9: NTM EPS (approx = 2×(B7+B8)) | B9: =2*(B7+B8)
A10: P/E at current price | B10: =IF($B$9<=0,"n/m",B4/$B$9)
A11: P/E implied at PT | B11: =IF($B$9<=0,"n/m",B5/$B$9)
A12: P/E implied at bear | B12: =IF($B$9<=0,"n/m",B6/$B$9)
A13: Stated multiple anchor | B13: 41 | C13: Retro-documented 7/7 = implied P/E@PT (baseline for drift tracking)
A14: Required NTM EPS for PT at stated mult | B14: =IF(ISNUMBER(B13),B5/B13,"—")
A15: Consensus NTM vs required (gap) | B15: =IF(AND(ISNUMBER(B14),ISNUMBER(B9),B9>0),B9/B14-1,"—")
A16: Asymmetry (PT−P)/(P−bear) | B16: =(B5-B4)/(B4-B6)
A18: Methodology (as logged in Decisions Log / note):
A19: June-3 batch rating; thin note (41 lines, memory-tape caveat)
A21: Implied price grid — NTM EPS (rows) × multiple (cols). All formulas.
A22: EPS \ Mult | B22: =IF(ISNUMBER(B12),ROUND(B12,1),ROUND(B10*0.7,1)) | C22: =ROUND(B10,1) | D22: =ROUND(B11,1)
A23: =ROUND($B$9*0.85,2) | B23: =$A23*B$22 | C23: =$A23*C$22 | D23: =$A23*D$22
A24: =ROUND($B$9*1,2) | B24: =$A24*B$22 | C24: =$A24*C$22 | D24: =$A24*D$22
A25: =ROUND($B$9*1.15,2) | B25: =$A25*B$22 | C25: =$A25*C$22 | D25: =$A25*D$22
A27: Audit note:
A28: ⚠️ No bear logged. Retired from watch band 7/7; deepen before Jul 29 print

Sheet WMB
A1: WMB — PT Audit Model (EPS × multiple) — Hold
A2: Built 2026-07-07 (evening). Consensus: Robinhood quarterly estimates 7/7 (next two quarters; NTM = 2 × sum — approximation, refine as quarters print). Prices: FMP official closes 7/7. Blue = input, Black = formula.
A4: Current price ($) | B4: 75.08
A5: Our PT ($) | B5: 80
A6: Bear ($) | B6: 58
A7: Cons EPS — Q+1e | B7: 0.51
A8: Cons EPS — Q+2e | B8: 0.55
A9: NTM EPS (approx = 2×(B7+B8)) | B9: =2*(B7+B8)
A10: P/E at current price | B10: =IF($B$9<=0,"n/m",B4/$B$9)
A11: P/E implied at PT | B11: =IF($B$9<=0,"n/m",B5/$B$9)
A12: P/E implied at bear | B12: =IF($B$9<=0,"n/m",B6/$B$9)
A13: Stated multiple anchor | B13: —
A14: Required NTM EPS for PT at stated mult | B14: —
A15: Consensus NTM vs required (gap) | B15: —
A16: Asymmetry (PT−P)/(P−bear) | B16: =(B5-B4)/(B4-B6)
A18: Methodology (as logged in Decisions Log / note):
A19: Screener + comps (7/7 initiation, screening mode)
A21: Implied price grid — NTM EPS (rows) × multiple (cols). All formulas.
A22: EPS \ Mult | B22: =IF(ISNUMBER(B12),ROUND(B12,1),ROUND(B10*0.7,1)) | C22: =ROUND(B10,1) | D22: =ROUND(B11,1)
A23: =ROUND($B$9*0.85,2) | B23: =$A23*B$22 | C23: =$A23*C$22 | D23: =$A23*D$22
A24: =ROUND($B$9*1,2) | B24: =$A24*B$22 | C24: =$A24*C$22 | D24: =$A24*D$22
A25: =ROUND($B$9*1.15,2) | B25: =$A25*B$22 | C25: =$A25*C$22 | D25: =$A25*D$22
A27: Audit note:
A28: Upgrade ≤$65 or Transco acceleration Aug 3. Green through the unwind

Sheet SMNEY
A1: SMNEY — PT Audit Model (EPS × multiple) — Hold
A2: Built 2026-07-07 (evening). Consensus: Robinhood quarterly estimates 7/7 (next two quarters; NTM = 2 × sum — approximation, refine as quarters print). Prices: FMP official closes 7/7. Blue = input, Black = formula.
A4: Current price ($) = ENR.DE × 0.2 × EURUSD | B4: =E4*0.2*E5 | D4: ENR.DE (€) | E4: 155.3
A5: Our PT ($) | B5: 38 | D5: EURUSD | E5: 1.14155
A6: Bear ($) | B6: 22
A7: Cons EPS — Q+1e | B7: —
A8: Cons EPS — Q+2e | B8: —
A9: NTM EPS (approx = 2×(B7+B8)) | B9: n/a
A10: P/E at current price | B10: n/a
A11: P/E implied at PT | B11: n/a
A12: P/E implied at bear | B12: n/a
A13: Stated multiple anchor | B13: —
A14: Required NTM EPS for PT at stated mult | B14: —
A15: Consensus NTM vs required (gap) | B15: —
A16: Asymmetry (PT−P)/(P−bear) | B16: =(B5-B4)/(B4-B6)
A18: Methodology (as logged in Decisions Log / note):
A19: ENR-consensus-anchored €173 (6/29); STANDING RULE: price = ENR.DE × 0.2 × EURUSD
A21: Grid omitted — EPS-negative / derived-price name; P/E framework not meaningful.
A27: Audit note:
A28: Derived pricing only (never FMP/OTC feeds). ENR.DE €155.30 × 0.2 × 1.1416 ⇒ ~$35.46
