Workbook

Sheet Summary
A1: PT AUDIT MODELS — Top 10 Buy-Rated Names (EPS × Multiple)
A2: Built 2026-07-07 per Vault Review §5 (make every PT auditable). Green = pulls from name tabs. Not yet covered: MRVL, CCJ, NBIS, + T3/T4 Buys — next pass. Refresh each tab at its print.
A4: Ticker | B4: Price 7/7 | C4: PT | D4: Bear | E4: NTM EPS (cons) | F4: P/E @ price | G4: P/E @ PT | H4: Asymmetry | I4: Audit flag
A5: GEV | B5: =GEV!B4 -> 1036.56 | C5: =GEV!B5 -> 1200 | D5: =GEV!B6 -> 600 | E5: =GEV!B9 -> 15.1 | F5: =GEV!B10 -> 68.646358 | G5: =GEV!B11 -> 79.470199 | H5: =GEV!B16 -> 0.37438153 | I5: ⚠️ 35x anchor ≠ PT (79x NTM) — re-anchor Jul 22
A6: CEG | B6: =CEG!B4 -> 242.26 | C6: =CEG!B5 -> 385 | D6: =CEG!B6 -> 220 | E6: =CEG!B9 -> 12.42 | F6: =CEG!B10 -> 19.505636 | G6: =CEG!B11 -> 30.99839 | H6: =CEG!B16 -> 6.4123989 | I6: EBITDA primary; P/E view distorted
A7: NRG | B7: =NRG!B4 -> 138.04 | C7: =NRG!B5 -> 185 | D7: =NRG!B6 -> 110 | E7: =NRG!B9 -> 9.98 | F7: =NRG!B10 -> 13.831663 | G7: =NRG!B11 -> 18.537074 | H7: =NRG!B16 -> 1.6747504 | I7: Clean
A8: VST | B8: =VST!B4 -> 154.73 | C8: =VST!B5 -> 230 | D8: =VST!B6 -> 145 | E8: =VST!B9 -> 9.16 | F8: =VST!B10 -> 16.891921 | G8: =VST!B11 -> 25.10917 | H8: =VST!B16 -> 7.7358684 | I8: High estimate dispersion
A9: MU | B9: =MU!B4 -> 921 | C9: =MU!B5 -> 1500 | D9: =MU!B6 -> 900 | E9: =MU!B9 -> 131.8 | F9: =MU!B10 -> 6.9878604 | G9: =MU!B11 -> 11.38088 | H9: =MU!B16 -> 27.571429 | I9: Conservative vs consensus (vault $120 < cons $131.8)
A10: AVGO | B10: =AVGO!B4 -> 364.49 | C10: =AVGO!B5 -> 560 | D10: =AVGO!B6 -> 350 | E10: =AVGO!B9 -> 13.9 | F10: =AVGO!B10 -> 26.222302 | G10: =AVGO!B11 -> 40.28777 | H10: =AVGO!B16 -> 13.492754 | I10: Anchor migration question (Sep 3)
A11: LRCX | B11: =LRCX!B4 -> 315.68 | C11: =LRCX!B5 -> 450 | D11: =LRCX!B6 -> 200 | E11: =LRCX!B9 -> 6.98 | F11: =LRCX!B10 -> 45.226361 | G11: =LRCX!B11 -> 64.469914 | H11: =LRCX!B16 -> 1.1611342 | I11: Reconciles ~60–64x; Jul 29 adjudicates
A12: VRT | B12: =VRT!B4 -> 288.49 | C12: =VRT!B5 -> 370 | D12: =VRT!B6 -> 220 | E12: =VRT!B9 -> 6.44 | F12: =VRT!B10 -> 44.796584 | G12: =VRT!B11 -> 57.453416 | H12: =VRT!B16 -> 1.1901007 | I12: ⚠️ No logged multiple anchor — set Jul 29
A13: ANET | B13: =ANET!B4 -> 163.39 | C13: =ANET!B5 -> 185 | D13: =ANET!B6 -> 90 | E13: =ANET!B9 -> 3.5 | F13: =ANET!B10 -> 46.682857 | G13: =ANET!B11 -> 52.857143 | H13: =ANET!B16 -> 0.29445429 | I13: Clean
A14: BE | B14: =BE!B4 -> 265.56 | C14: =BE!B5 -> 330 | D14: =BE!B6 -> 120 | E14: =BE!B9 -> 1.68 | F14: =BE!B10 -> 158.07143 | G14: =BE!B11 -> 196.42857 | H14: =BE!B16 -> 0.44270404 | I14: EV/Rev anchor; P/E n/a

Sheet GEV
A1: GEV — PT Audit Model (EPS × multiple)
A2: Built 2026-07-07. Consensus: Robinhood quarterly estimates 7/7 (next two quarters; NTM = 2 × sum — approximation, refine as quarters print). Prices: FMP live 7/7. Blue = input, Black = formula.
A4: Current price ($) | B4: 1036.56
A5: Our PT ($) | B5: 1200
A6: Bear ($) | B6: 600
A7: Cons EPS — Q2'26e (Jul 22) | B7: 3.22
A8: Cons EPS — Q3'26e | B8: 4.33
A9: NTM EPS (approx = 2×(B7+B8)) | B9: =2*(B7+B8) -> 15.1
A10: P/E at current price | B10: =B4/B9 -> 68.646358
A11: P/E implied at PT | B11: =B5/B9 -> 79.470199
A12: P/E implied at bear | B12: =B6/B9 -> 39.735099
A13: Stated multiple anchor | B13: 35
A14: Required NTM EPS for PT at stated mult | B14: =IF(ISNUMBER(B13),B5/B13,"—") -> 34.285714
A15: Consensus NTM vs required (gap) | B15: =IF(ISNUMBER(B14),B9/B14-1,"—") -> -0.55958333
A16: Asymmetry (PT−P)/(P−bear) | B16: =(B5-B4)/(B4-B6) -> 0.37438153
A18: Methodology (as logged in Decisions Log):
A19: Thesis-driven — logged as 'NTM P/E 35x' (6/3)
A21: Implied price grid — NTM EPS (rows) × multiple (cols). All formulas.
A22: EPS \ Mult | B22: =ROUND(B12,1) -> 39.7 | C22: =ROUND(B10,1) -> 68.6 | D22: =ROUND(B11,1) -> 79.5
A23: =ROUND($B$9*0.85,2) -> 12.84 | B23: =$A23*B$22 -> 509.748 | C23: =$A23*C$22 -> 880.824 | D23: =$A23*D$22 -> 1020.78
A24: =ROUND($B$9*1,2) -> 15.1 | B24: =$A24*B$22 -> 599.47 | C24: =$A24*C$22 -> 1035.86 | D24: =$A24*D$22 -> 1200.45
A25: =ROUND($B$9*1.15,2) -> 17.37 | B25: =$A25*B$22 -> 689.589 | C25: =$A25*C$22 -> 1191.582 | D25: =$A25*D$22 -> 1380.915
A27: Audit note:
A28: MAJOR RECONCILIATION FLAG: 35x × consensus NTM $15.10 = $529, vs PT $1,200 (79x NTM). The PT is effectively anchored to FY2028 earnings power / backlog conversion, not NTM. Re-anchor the PT methodology EXPLICITLY at the Jul 22 print (backlog >=105GW branch).

Sheet CEG
A1: CEG — PT Audit Model (EPS × multiple)
A2: Built 2026-07-07. Consensus: Robinhood quarterly estimates 7/7 (next two quarters; NTM = 2 × sum — approximation, refine as quarters print). Prices: FMP live 7/7. Blue = input, Black = formula.
A4: Current price ($) | B4: 242.26
A5: Our PT ($) | B5: 385
A6: Bear ($) | B6: 220
A7: Cons EPS — Q2'26e (Aug 6) | B7: 2.37
A8: Cons EPS — Q3'26e | B8: 3.84
A9: NTM EPS (approx = 2×(B7+B8)) | B9: =2*(B7+B8) -> 12.42
A10: P/E at current price | B10: =B4/B9 -> 19.505636
A11: P/E implied at PT | B11: =B5/B9 -> 30.99839
A12: P/E implied at bear | B12: =B6/B9 -> 17.713366
A13: Stated multiple anchor | B13: —
A14: Required NTM EPS for PT at stated mult | B14: =IF(ISNUMBER(B13),B5/B13,"—") -> —
A15: Consensus NTM vs required (gap) | B15: =IF(ISNUMBER(B14),B9/B14-1,"—") -> —
A16: Asymmetry (PT−P)/(P−bear) | B16: =(B5-B4)/(B4-B6) -> 6.4123989
A18: Methodology (as logged in Decisions Log):
A19: DCF + variant perception (EV/EBITDA; 14x exit in DCF)
A21: Implied price grid — NTM EPS (rows) × multiple (cols). All formulas.
A22: EPS \ Mult | B22: =ROUND(B12,1) -> 17.7 | C22: =ROUND(B10,1) -> 19.5 | D22: =ROUND(B11,1) -> 31
A23: =ROUND($B$9*0.85,2) -> 10.56 | B23: =$A23*B$22 -> 186.912 | C23: =$A23*C$22 -> 205.92 | D23: =$A23*D$22 -> 327.36
A24: =ROUND($B$9*1,2) -> 12.42 | B24: =$A24*B$22 -> 219.834 | C24: =$A24*C$22 -> 242.19 | D24: =$A24*D$22 -> 385.02
A25: =ROUND($B$9*1.15,2) -> 14.28 | B25: =$A25*B$22 -> 252.756 | C25: =$A25*C$22 -> 278.46 | D25: =$A25*D$22 -> 442.68
A27: Audit note:
A28: PT = 31x NTM P/E vs 19.5x at price. P/E view distorted by D&A/nuclear depreciation — EV/EBITDA stays primary. PJM sensitivity staged separately (see CEG_PJM_Sensitivity_2026-07-14).

Sheet NRG
A1: NRG — PT Audit Model (EPS × multiple)
A2: Built 2026-07-07. Consensus: Robinhood quarterly estimates 7/7 (next two quarters; NTM = 2 × sum — approximation, refine as quarters print). Prices: FMP live 7/7. Blue = input, Black = formula.
A4: Current price ($) | B4: 138.04
A5: Our PT ($) | B5: 185
A6: Bear ($) | B6: 110
A7: Cons EPS — Q2'26e (Aug 4) | B7: 1.75
A8: Cons EPS — Q3'26e | B8: 3.24
A9: NTM EPS (approx = 2×(B7+B8)) | B9: =2*(B7+B8) -> 9.98
A10: P/E at current price | B10: =B4/B9 -> 13.831663
A11: P/E implied at PT | B11: =B5/B9 -> 18.537074
A12: P/E implied at bear | B12: =B6/B9 -> 11.022044
A13: Stated multiple anchor | B13: —
A14: Required NTM EPS for PT at stated mult | B14: =IF(ISNUMBER(B13),B5/B13,"—") -> —
A15: Consensus NTM vs required (gap) | B15: =IF(ISNUMBER(B14),B9/B14-1,"—") -> —
A16: Asymmetry (PT−P)/(P−bear) | B16: =(B5-B4)/(B4-B6) -> 1.6747504
A18: Methodology (as logged in Decisions Log):
A19: Variant perception (6/3)
A21: Implied price grid — NTM EPS (rows) × multiple (cols). All formulas.
A22: EPS \ Mult | B22: =ROUND(B12,1) -> 11 | C22: =ROUND(B10,1) -> 13.8 | D22: =ROUND(B11,1) -> 18.5
A23: =ROUND($B$9*0.85,2) -> 8.48 | B23: =$A23*B$22 -> 93.28 | C23: =$A23*C$22 -> 117.024 | D23: =$A23*D$22 -> 156.88
A24: =ROUND($B$9*1,2) -> 9.98 | B24: =$A24*B$22 -> 109.78 | C24: =$A24*C$22 -> 137.724 | D24: =$A24*D$22 -> 184.63
A25: =ROUND($B$9*1.15,2) -> 11.48 | B25: =$A25*B$22 -> 126.28 | C25: =$A25*C$22 -> 158.424 | D25: =$A25*D$22 -> 212.38
A27: Audit note:
A28: Cleanest T1 audit: PT = 18.5x NTM vs 13.8x current — modest re-rating assumption. No flag.

Sheet VST
A1: VST — PT Audit Model (EPS × multiple)
A2: Built 2026-07-07. Consensus: Robinhood quarterly estimates 7/7 (next two quarters; NTM = 2 × sum — approximation, refine as quarters print). Prices: FMP live 7/7. Blue = input, Black = formula.
A4: Current price ($) | B4: 154.73
A5: Our PT ($) | B5: 230
A6: Bear ($) | B6: 145
A7: Cons EPS — Q2'26e (Aug 7) | B7: 2.21
A8: Cons EPS — Q3'26e | B8: 2.37
A9: NTM EPS (approx = 2×(B7+B8)) | B9: =2*(B7+B8) -> 9.16
A10: P/E at current price | B10: =B4/B9 -> 16.891921
A11: P/E implied at PT | B11: =B5/B9 -> 25.10917
A12: P/E implied at bear | B12: =B6/B9 -> 15.829694
A13: Stated multiple anchor | B13: —
A14: Required NTM EPS for PT at stated mult | B14: =IF(ISNUMBER(B13),B5/B13,"—") -> —
A15: Consensus NTM vs required (gap) | B15: =IF(ISNUMBER(B14),B9/B14-1,"—") -> —
A16: Asymmetry (PT−P)/(P−bear) | B16: =(B5-B4)/(B4-B6) -> 7.7358684
A18: Methodology (as logged in Decisions Log):
A19: Variant perception; bear re-underwritten 6/23 (9x $6.5B EBITDA => ~$105; MP bear $145)
A21: Implied price grid — NTM EPS (rows) × multiple (cols). All formulas.
A22: EPS \ Mult | B22: =ROUND(B12,1) -> 15.8 | C22: =ROUND(B10,1) -> 16.9 | D22: =ROUND(B11,1) -> 25.1
A23: =ROUND($B$9*0.85,2) -> 7.79 | B23: =$A23*B$22 -> 123.082 | C23: =$A23*C$22 -> 131.651 | D23: =$A23*D$22 -> 195.529
A24: =ROUND($B$9*1,2) -> 9.16 | B24: =$A24*B$22 -> 144.728 | C24: =$A24*C$22 -> 154.804 | D24: =$A24*D$22 -> 229.916
A25: =ROUND($B$9*1.15,2) -> 10.53 | B25: =$A25*B$22 -> 166.374 | C25: =$A25*C$22 -> 177.957 | D25: =$A25*D$22 -> 264.303
A27: Audit note:
A28: PT = 25x NTM vs 17x current. High estimate dispersion (Q4'25 printed $0.54 vs $2.38 est) — treat NTM with wide error bars; Cogentrix decision at Aug 7 print.

Sheet MU
A1: MU — PT Audit Model (EPS × multiple)
A2: Built 2026-07-07. Consensus: Robinhood quarterly estimates 7/7 (next two quarters; NTM = 2 × sum — approximation, refine as quarters print). Prices: FMP live 7/7. Blue = input, Black = formula.
A4: Current price ($) | B4: 921
A5: Our PT ($) | B5: 1500
A6: Bear ($) | B6: 900
A7: Cons EPS — FQ4'26e (Sep 22) | B7: 31.24
A8: Cons EPS — FQ1'27e | B8: 34.66
A9: NTM EPS (approx = 2×(B7+B8)) | B9: =2*(B7+B8) -> 131.8
A10: P/E at current price | B10: =B4/B9 -> 6.9878604
A11: P/E implied at PT | B11: =B5/B9 -> 11.38088
A12: P/E implied at bear | B12: =B6/B9 -> 6.8285281
A13: Stated multiple anchor | B13: 12.5
A14: Required NTM EPS for PT at stated mult | B14: =IF(ISNUMBER(B13),B5/B13,"—") -> 120
A15: Consensus NTM vs required (gap) | B15: =IF(ISNUMBER(B14),B9/B14-1,"—") -> 0.098333333
A16: Asymmetry (PT−P)/(P−bear) | B16: =(B5-B4)/(B4-B6) -> 27.571429
A18: Methodology (as logged in Decisions Log):
A19: Catalyst Playbook upgrade (6/25) — 12.5x NTM ~$120
A21: Implied price grid — NTM EPS (rows) × multiple (cols). All formulas.
A22: EPS \ Mult | B22: =ROUND(B12,1) -> 6.8 | C22: =ROUND(B10,1) -> 7 | D22: =ROUND(B11,1) -> 11.4
A23: =ROUND($B$9*0.85,2) -> 112.03 | B23: =$A23*B$22 -> 761.804 | C23: =$A23*C$22 -> 784.21 | D23: =$A23*D$22 -> 1277.142
A24: =ROUND($B$9*1,2) -> 131.8 | B24: =$A24*B$22 -> 896.24 | C24: =$A24*C$22 -> 922.6 | D24: =$A24*D$22 -> 1502.52
A25: =ROUND($B$9*1.15,2) -> 151.57 | B25: =$A25*B$22 -> 1030.676 | C25: =$A25*C$22 -> 1060.99 | D25: =$A25*D$22 -> 1727.898
A27: Audit note:
A28: Cheapest tab in the book: 7.0x consensus NTM $131.8 at $921; PT = 11.4x. Vault's $120 NTM anchor is BELOW consensus — conservative. The whole debate is cyclicality: bear case = peak-EPS x trough-multiple, hence the $900 floor protocol (armed 7/7).

Sheet AVGO
A1: AVGO — PT Audit Model (EPS × multiple)
A2: Built 2026-07-07. Consensus: Robinhood quarterly estimates 7/7 (next two quarters; NTM = 2 × sum — approximation, refine as quarters print). Prices: FMP live 7/7. Blue = input, Black = formula.
A4: Current price ($) | B4: 364.49
A5: Our PT ($) | B5: 560
A6: Bear ($) | B6: 350
A7: Cons EPS — FQ3'26e (Sep 3) | B7: 3.16
A8: Cons EPS — FQ4'26e | B8: 3.79
A9: NTM EPS (approx = 2×(B7+B8)) | B9: =2*(B7+B8) -> 13.9
A10: P/E at current price | B10: =B4/B9 -> 26.222302
A11: P/E implied at PT | B11: =B5/B9 -> 40.28777
A12: P/E implied at bear | B12: =B6/B9 -> 25.179856
A13: Stated multiple anchor | B13: —
A14: Required NTM EPS for PT at stated mult | B14: =IF(ISNUMBER(B13),B5/B13,"—") -> —
A15: Consensus NTM vs required (gap) | B15: =IF(ISNUMBER(B14),B9/B14-1,"—") -> —
A16: Asymmetry (PT−P)/(P−bear) | B16: =(B5-B4)/(B4-B6) -> 13.492754
A18: Methodology (as logged in Decisions Log):
A19: EV/Revenue ~14x NTM (initiation); triggers re-checked 7/7 (Buy reaffirmed)
A21: Implied price grid — NTM EPS (rows) × multiple (cols). All formulas.
A22: EPS \ Mult | B22: =ROUND(B12,1) -> 25.2 | C22: =ROUND(B10,1) -> 26.2 | D22: =ROUND(B11,1) -> 40.3
A23: =ROUND($B$9*0.85,2) -> 11.82 | B23: =$A23*B$22 -> 297.864 | C23: =$A23*C$22 -> 309.684 | D23: =$A23*D$22 -> 476.346
A24: =ROUND($B$9*1,2) -> 13.9 | B24: =$A24*B$22 -> 350.28 | C24: =$A24*C$22 -> 364.18 | D24: =$A24*D$22 -> 560.17
A25: =ROUND($B$9*1.15,2) -> 15.99 | B25: =$A25*B$22 -> 402.948 | C25: =$A25*C$22 -> 418.938 | D25: =$A25*D$22 -> 644.397
A27: Audit note:
A28: EPS path steepening: FQ3e $3.16 vs $2.44 just printed (+30% q/q). PT = 40x NTM P/E. Consider migrating the PT anchor from EV/Revenue to P/E as software mix stabilizes — decide at Sep 3 print.

Sheet LRCX
A1: LRCX — PT Audit Model (EPS × multiple)
A2: Built 2026-07-07. Consensus: Robinhood quarterly estimates 7/7 (next two quarters; NTM = 2 × sum — approximation, refine as quarters print). Prices: FMP live 7/7. Blue = input, Black = formula.
A4: Current price ($) | B4: 315.68
A5: Our PT ($) | B5: 450
A6: Bear ($) | B6: 200
A7: Cons EPS — FQ4'26e (Jul 29) | B7: 1.68
A8: Cons EPS — FQ1'27e | B8: 1.81
A9: NTM EPS (approx = 2×(B7+B8)) | B9: =2*(B7+B8) -> 6.98
A10: P/E at current price | B10: =B4/B9 -> 45.226361
A11: P/E implied at PT | B11: =B5/B9 -> 64.469914
A12: P/E implied at bear | B12: =B6/B9 -> 28.653295
A13: Stated multiple anchor | B13: 60
A14: Required NTM EPS for PT at stated mult | B14: =IF(ISNUMBER(B13),B5/B13,"—") -> 7.5
A15: Consensus NTM vs required (gap) | B15: =IF(ISNUMBER(B14),B9/B14-1,"—") -> -0.069333333
A16: Asymmetry (PT−P)/(P−bear) | B16: =(B5-B4)/(B4-B6) -> 1.1611342
A18: Methodology (as logged in Decisions Log):
A19: Revised estimates (6/18) — ~60x FY27 EPS ~$7.25 => $435-472
A21: Implied price grid — NTM EPS (rows) × multiple (cols). All formulas.
A22: EPS \ Mult | B22: =ROUND(B12,1) -> 28.7 | C22: =ROUND(B10,1) -> 45.2 | D22: =ROUND(B11,1) -> 64.5
A23: =ROUND($B$9*0.85,2) -> 5.93 | B23: =$A23*B$22 -> 170.191 | C23: =$A23*C$22 -> 268.036 | D23: =$A23*D$22 -> 382.485
A24: =ROUND($B$9*1,2) -> 6.98 | B24: =$A24*B$22 -> 200.326 | C24: =$A24*C$22 -> 315.496 | D24: =$A24*D$22 -> 450.21
A25: =ROUND($B$9*1.15,2) -> 8.03 | B25: =$A25*B$22 -> 230.461 | C25: =$A25*C$22 -> 362.956 | D25: =$A25*D$22 -> 517.935
A27: Audit note:
A28: Roughly reconciles: 60x × cons NTM $6.98 = $419; PT $450 needs ~64x or FY27 EPS upside toward the vault's $7.25. Within tolerance; Jul 29 print adjudicates (rev >=$6.8B + guide >=$7.0B = bull branch).

Sheet VRT
A1: VRT — PT Audit Model (EPS × multiple)
A2: Built 2026-07-07. Consensus: Robinhood quarterly estimates 7/7 (next two quarters; NTM = 2 × sum — approximation, refine as quarters print). Prices: FMP live 7/7. Blue = input, Black = formula.
A4: Current price ($) | B4: 288.49
A5: Our PT ($) | B5: 370
A6: Bear ($) | B6: 220
A7: Cons EPS — Q2'26e (Jul 29) | B7: 1.43
A8: Cons EPS — Q3'26e | B8: 1.79
A9: NTM EPS (approx = 2×(B7+B8)) | B9: =2*(B7+B8) -> 6.44
A10: P/E at current price | B10: =B4/B9 -> 44.796584
A11: P/E implied at PT | B11: =B5/B9 -> 57.453416
A12: P/E implied at bear | B12: =B6/B9 -> 34.161491
A13: Stated multiple anchor | B13: —
A14: Required NTM EPS for PT at stated mult | B14: =IF(ISNUMBER(B13),B5/B13,"—") -> —
A15: Consensus NTM vs required (gap) | B15: =IF(ISNUMBER(B14),B9/B14-1,"—") -> —
A16: Asymmetry (PT−P)/(P−bear) | B16: =(B5-B4)/(B4-B6) -> 1.1901007
A18: Methodology (as logged in Decisions Log):
A19: Thesis-driven (AI cooling pure-play); no logged multiple anchor
A21: Implied price grid — NTM EPS (rows) × multiple (cols). All formulas.
A22: EPS \ Mult | B22: =ROUND(B12,1) -> 34.2 | C22: =ROUND(B10,1) -> 44.8 | D22: =ROUND(B11,1) -> 57.5
A23: =ROUND($B$9*0.85,2) -> 5.47 | B23: =$A23*B$22 -> 187.074 | C23: =$A23*C$22 -> 245.056 | D23: =$A23*D$22 -> 314.525
A24: =ROUND($B$9*1,2) -> 6.44 | B24: =$A24*B$22 -> 220.248 | C24: =$A24*C$22 -> 288.512 | D24: =$A24*D$22 -> 370.3
A25: =ROUND($B$9*1.15,2) -> 7.41 | B25: =$A25*B$22 -> 253.422 | C25: =$A25*C$22 -> 331.968 | D25: =$A25*D$22 -> 426.075
A27: Audit note:
A28: FLAG: PT = 57x NTM with no logged multiple anchor — the only top-10 PT with no stated methodology number. Set the anchor at the Jul 29 print.

Sheet ANET
A1: ANET — PT Audit Model (EPS × multiple)
A2: Built 2026-07-07. Consensus: Robinhood quarterly estimates 7/7 (next two quarters; NTM = 2 × sum — approximation, refine as quarters print). Prices: FMP live 7/7. Blue = input, Black = formula.
A4: Current price ($) | B4: 163.39
A5: Our PT ($) | B5: 185
A6: Bear ($) | B6: 90
A7: Cons EPS — Q2'26e (Aug 4) | B7: 0.86
A8: Cons EPS — Q3'26e | B8: 0.89
A9: NTM EPS (approx = 2×(B7+B8)) | B9: =2*(B7+B8) -> 3.5
A10: P/E at current price | B10: =B4/B9 -> 46.682857
A11: P/E implied at PT | B11: =B5/B9 -> 52.857143
A12: P/E implied at bear | B12: =B6/B9 -> 25.714286
A13: Stated multiple anchor | B13: —
A14: Required NTM EPS for PT at stated mult | B14: =IF(ISNUMBER(B13),B5/B13,"—") -> —
A15: Consensus NTM vs required (gap) | B15: =IF(ISNUMBER(B14),B9/B14-1,"—") -> —
A16: Asymmetry (PT−P)/(P−bear) | B16: =(B5-B4)/(B4-B6) -> 0.29445429
A18: Methodology (as logged in Decisions Log):
A19: Thesis-driven (AI Ethernet)
A21: Implied price grid — NTM EPS (rows) × multiple (cols). All formulas.
A22: EPS \ Mult | B22: =ROUND(B12,1) -> 25.7 | C22: =ROUND(B10,1) -> 46.7 | D22: =ROUND(B11,1) -> 52.9
A23: =ROUND($B$9*0.85,2) -> 2.98 | B23: =$A23*B$22 -> 76.586 | C23: =$A23*C$22 -> 139.166 | D23: =$A23*D$22 -> 157.642
A24: =ROUND($B$9*1,2) -> 3.5 | B24: =$A24*B$22 -> 89.95 | C24: =$A24*C$22 -> 163.45 | D24: =$A24*D$22 -> 185.15
A25: =ROUND($B$9*1.15,2) -> 4.03 | B25: =$A25*B$22 -> 103.571 | C25: =$A25*C$22 -> 188.201 | D25: =$A25*D$22 -> 213.187
A27: Audit note:
A28: PT = 52.9x NTM vs 46.7x current — modest premium, internally consistent. No flag.

Sheet BE
A1: BE — PT Audit Model (EPS × multiple)
A2: Built 2026-07-07. Consensus: Robinhood quarterly estimates 7/7 (next two quarters; NTM = 2 × sum — approximation, refine as quarters print). Prices: FMP live 7/7. Blue = input, Black = formula.
A4: Current price ($) | B4: 265.56
A5: Our PT ($) | B5: 330
A6: Bear ($) | B6: 120
A7: Cons EPS — Q2'26e (Jul 28) | B7: 0.36
A8: Cons EPS — Q3'26e | B8: 0.48
A9: NTM EPS (approx = 2×(B7+B8)) | B9: =2*(B7+B8) -> 1.68
A10: P/E at current price | B10: =B4/B9 -> 158.07143
A11: P/E implied at PT | B11: =B5/B9 -> 196.42857
A12: P/E implied at bear | B12: =B6/B9 -> 71.428571
A13: Stated multiple anchor | B13: —
A14: Required NTM EPS for PT at stated mult | B14: =IF(ISNUMBER(B13),B5/B13,"—") -> —
A15: Consensus NTM vs required (gap) | B15: =IF(ISNUMBER(B14),B9/B14-1,"—") -> —
A16: Asymmetry (PT−P)/(P−bear) | B16: =(B5-B4)/(B4-B6) -> 0.44270404
A18: Methodology (as logged in Decisions Log):
A19: EV/Revenue (per valuation snapshot)
A21: Implied price grid — NTM EPS (rows) × multiple (cols). All formulas.
A22: EPS \ Mult | B22: =ROUND(B12,1) -> 71.4 | C22: =ROUND(B10,1) -> 158.1 | D22: =ROUND(B11,1) -> 196.4
A23: =ROUND($B$9*0.85,2) -> 1.43 | B23: =$A23*B$22 -> 102.102 | C23: =$A23*C$22 -> 226.083 | D23: =$A23*D$22 -> 280.852
A24: =ROUND($B$9*1,2) -> 1.68 | B24: =$A24*B$22 -> 119.952 | C24: =$A24*C$22 -> 265.608 | D24: =$A24*D$22 -> 329.952
A25: =ROUND($B$9*1.15,2) -> 1.93 | B25: =$A25*B$22 -> 137.802 | C25: =$A25*C$22 -> 305.133 | D25: =$A25*D$22 -> 379.052
A27: Audit note:
A28: P/E view is for completeness only (158x NTM — meaningless for a company at breakeven inflection). EV/Revenue is the anchor; refresh it at the Jul 28 print (date corrected 7/7; was Aug 6). Jupiter/NM approval still the binary.
